Workbook

Sheet Contas Orç
A1: CÓDIGO | B1: CONTA ANALÍTICA
A2: Conta | B2: Descricao | C2: Tipo | D2: Preview Cod. | E2: Cond. Normal | F2: Cod. Mascara | G2: Dt. Inclusao | H2: Inicio Vig. | I2: C.O.Superior
A3: 120301 | B3: IMOVEIS | C3: Sintetica | D3: 120301 | E3: Despesa | G3: 44872 | H3: 44872
A4: 120301001 | B4: TERRENOS | C4: Analitica | D4: 120301001 | E4: Despesa | G4: 44872 | H4: 44872 | I4: 120301
A5: 120301002 | B5: EDIFICIOS | C5: Analitica | D5: 120301002 | E5: Despesa | G5: 44872 | H5: 44872 | I5: 120301
A6: 120301003 | B6: INSTALACOES | C6: Analitica | D6: 120301003 | E6: Despesa | G6: 44872 | H6: 44872 | I6: 120301
A7: 120301004 | B7: TERRENOS AVP | C7: Analitica | D7: 120301004 | E7: Despesa | G7: 44872 | H7: 44872 | I7: 120301
A8: 120301005 | B8: INSTALACOES - NOVO TERMINAL | C8: Analitica | D8: 120301005 | E8: Despesa | G8: 44872 | H8: 44872 | I8: 120301
A9: 120302 | B9: MOVEIS E UTENSILIOS | C9: Sintetica | D9: 120302 | E9: Despesa | G9: 44872 | H9: 44872
A10: 120302001 | B10: MOVEIS E UTENSILIOS | C10: Analitica | D10: 120302001 | E10: Despesa | G10: 44872 | H10: 44872 | I10: 120302
A11: 120303 | B11: MAQUINAS, EQUIPAMENTOS E FERRAMENTAS | C11: Sintetica | D11: 120303 | E11: Despesa | G11: 44872 | H11: 44872
A12: 120303001 | B12: MAQUINAS E EQUIPAMENTOS | C12: Analitica | D12: 120303001 | E12: Despesa | G12: 44872 | H12: 44872 | I12: 120303
A13: 120303002 | B13: EQUIPAMENTOS DE INFORMATICA | C13: Analitica | D13: 120303002 | E13: Despesa | G13: 44872 | H13: 44872 | I13: 120303
A14: 120303003 | B14: FERRAMENTAS | C14: Analitica | D14: 120303003 | E14: Despesa | G14: 44872 | H14: 44872 | I14: 120303
A15: 120303004 | B15: MAQUINAS/EQUIPAMENTOS AVP | C15: Analitica | D15: 120303004 | E15: Despesa | G15: 44872 | H15: 44872 | I15: 120303
A16: 120304 | B16: VEICULOS | C16: Sintetica | D16: 120304 | E16: Despesa | G16: 44872 | H16: 44872
A17: 120304001 | B17: VEICULOS | C17: Analitica | D17: 120304001 | E17: Despesa | G17: 44872 | H17: 44872 | I17: 120304
A18: 120304002 | B18: CONSORCIO DE VEICULOS | C18: Analitica | D18: 120304002 | E18: Despesa | G18: 44872 | H18: 44872 | I18: 120304
A19: 120304003 | B19: VEICULOS AVP | C19: Analitica | D19: 120304003 | E19: Despesa | G19: 44872 | H19: 44872 | I19: 120304
A20: 120305 | B20: BENS ARRENDAMENTO MERCANTIL FINANCEIRO | C20: Sintetica | D20: 120305 | E20: Despesa | G20: 44872 | H20: 44872
A21: 120305001 | B21: MAQUINAS E EQUIPAMENTOS - ARRENDAMENTO | C21: Analitica | D21: 120305001 | E21: Despesa | G21: 44872 | H21: 44872 | I21: 120305
A22: 120305002 | B22: VEICULOS UTILITARIOS | C22: Analitica | D22: 120305002 | E22: Despesa | G22: 44872 | H22: 44872 | I22: 120305
A23: 120307 | B23: IMOBILIZADO EM ANDAMENTO | C23: Sintetica | D23: 120307 | E23: Despesa | G23: 44872 | H23: 44872
A24: 120307001 | B24: IMOBILIZADO EM ANDAMENTO - PROPRIOS | C24: Analitica | D24: 120307001 | E24: Despesa | G24: 44872 | H24: 44872 | I24: 120307
A25: 120307002 | B25: IMOBILIZADO EM ANDAMENTO - TERCEIROS | C25: Analitica | D25: 120307002 | E25: Despesa | G25: 44872 | H25: 44872 | I25: 120307
A26: 1204 | B26: INTANGIVEL | C26: Sintetica | D26: 1204 | E26: Despesa | G26: 44872 | H26: 44872
A27: 120401001 | B27: SOFTWARES | C27: Analitica | D27: 120401001 | E27: Despesa | G27: 44872 | H27: 44872 | I27: 1204
A28: 120402001 | B28: MARCAS E PATENTES | C28: Analitica | D28: 120402001 | E28: Despesa | G28: 44872 | H28: 44872 | I28: 1204
A29: 3101 | B29: RECEITA DE SERVICOS | C29: Sintetica | D29: 3101 | E29: Receita | G29: 44872 | H29: 44872
A30: 310101 | B30: RECEITA BRUTA DE TRANSPORTES | C30: Analitica | D30: 310101 | E30: Receita | G30: 44872 | H30: 44872 | I30: 3101
A31: 310102 | B31: RECEITA BRUTA DE OPERACOES PORTUARIAS | C31: Analitica | D31: 310102 | E31: Receita | G31: 44872 | H31: 44872 | I31: 3101
A32: 310109 | B32: ( - ) DEDUCOES DA RECEITA BRUTA | C32: Analitica | D32: 310109 | E32: Despesa | G32: 44872 | H32: 44872 | I32: 3101
A33: 3109 | B33: OUTRAS RECEITAS | C33: Sintetica | D33: 3109 | E33: Receita | G33: 44872 | H33: 44872
A34: 310901 | B34: OUTRAS RECEITAS | C34: Analitica | D34: 310901 | E34: Receita | G34: 44872 | H34: 44872 | I34: 3109
A35: 3201 | B35: CUSTOS COM PESSOAL | C35: Sintetica | D35: 3201 | E35: Despesa | G35: 44872 | H35: 44872
A36: 320101 | B36: REMUNERACOES | C36: Analitica | D36: 320101 | E36: Despesa | G36: 44872 | H36: 44872 | I36: 3201
A37: 320102 | B37: ENCARGOS SOCIAIS | C37: Analitica | D37: 320102 | E37: Despesa | G37: 44872 | H37: 44872 | I37: 3201
A38: 320103 | B38: BENEFICIOS | C38: Analitica | D38: 320103 | E38: Despesa | G38: 44872 | H38: 44872 | I38: 3201
A39: 320104 | B39: OUTROS GASTOS COM PESSOAL | C39: Analitica | D39: 320104 | E39: Despesa | G39: 44872 | H39: 44872 | I39: 3201
A40: 320105 | B40: ( - ) INSS DESONERACAO | C40: Analitica | D40: 320105 | E40: Despesa | G40: 44872 | H40: 44872 | I40: 3201
A41: 3202 | B41: SERVICOS DE TERCEIROS | C41: Sintetica | D41: 3202 | E41: Despesa | G41: 44872 | H41: 44872
A42: 320201001 | B42: PJ-CONSULTORIA E ASSESSORIA | C42: Analitica | D42: 320201001 | E42: Despesa | G42: 44872 | H42: 44872 | I42: 3202
A43: 320201002 | B43: PJ-HONORARIOS ADVOCATICIOS | C43: Analitica | D43: 320201002 | E43: Despesa | G43: 44872 | H43: 44872 | I43: 3202
A44: 320201003 | B44: PJ-SEGURANCA PATRIMONIAL | C44: Analitica | D44: 320201003 | E44: Despesa | G44: 44872 | H44: 44872 | I44: 3202
A45: 320201004 | B45: PJ-LOCACAO DE MAQUINAS E EQUIPAMENTO | C45: Analitica | D45: 320201004 | E45: Despesa | G45: 44872 | H45: 44872 | I45: 3202
A46: 320201005 | B46: PJ-MAO-DE-OBRA TERCEIRIZADA | C46: Analitica | D46: 320201005 | E46: Despesa | G46: 44872 | H46: 44872 | I46: 3202
A47: 320201006 | B47: PJ-OUTROS SERVICOS CONTRATADOS-PJ | C47: Analitica | D47: 320201006 | E47: Despesa | G47: 44872 | H47: 44872 | I47: 3202
A48: 320202001 | B48: PF-CONSULTORIA E ASSESSORIA | C48: Analitica | D48: 320202001 | E48: Despesa | G48: 44872 | H48: 44872 | I48: 3202
A49: 320202002 | B49: PF-MAO-DE-OBRA TERCEIRIZADA | C49: Analitica | D49: 320202002 | E49: Despesa | G49: 44872 | H49: 44872 | I49: 3202
A50: 320202003 | B50: PF-OUTROS SERVICOS CONTRATADOS-PF | C50: Analitica | D50: 320202003 | E50: Despesa | G50: 44872 | H50: 44872 | I50: 3202
A51: 3203 | B51: CUSTO COM FROTA E EQUIPAMENTO | C51: Sintetica | D51: 3203 | E51: Despesa | G51: 44872 | H51: 44872
A52: 320301001 | B52: COMBUSTIVEIS | C52: Analitica | D52: 320301001 | E52: Despesa | G52: 44872 | H52: 44872 | I52: 3203
A53: 320301002 | B53: LUBRIFICANTES | C53: Analitica | D53: 320301002 | E53: Despesa | G53: 44872 | H53: 44872 | I53: 3203
A54: 320301003 | B54: PNEUS E RECAPAGENS | C54: Analitica | D54: 320301003 | E54: Despesa | G54: 44872 | H54: 44872 | I54: 3203
A55: 320301004 | B55: PECAS E ACESSORIOS | C55: Analitica | D55: 320301004 | E55: Despesa | G55: 44872 | H55: 44872 | I55: 3203
A56: 320301005 | B56: FERRAMENTAS | C56: Analitica | D56: 320301005 | E56: Despesa | G56: 44872 | H56: 44872 | I56: 3203
A57: 320301006 | B57: SERVICOS E MANUTENCAO DE VEICULOS EQ | C57: Analitica | D57: 320301006 | E57: Despesa | G57: 44872 | H57: 44872 | I57: 3203
A58: 320301007 | B58: LICENCIAMENTO - IPVA - DPVAT | C58: Analitica | D58: 320301007 | E58: Despesa | G58: 44872 | H58: 44872 | I58: 3203
A59: 320301008 | B59: MULTAS DE TRANSITO | C59: Analitica | D59: 320301008 | E59: Despesa | G59: 44872 | H59: 44872 | I59: 3203
A60: 320301009 | B60: RASTREAMENTO | C60: Analitica | D60: 320301009 | E60: Despesa | G60: 44872 | H60: 44872 | I60: 3203
A61: 320301010 | B61: PEDAGIO | C61: Analitica | D61: 320301010 | E61: Despesa | G61: 44872 | H61: 44872 | I61: 3203
A62: 320301011 | B62: GERENCIAMENTO DE RISCO | C62: Analitica | D62: 320301011 | E62: Despesa | G62: 44872 | H62: 44872 | I62: 3203
A63: 3204 | B63: CUSTO DE FUNCIONAMENTO | C63: Sintetica | D63: 3204 | E63: Despesa | G63: 44872 | H63: 44872
A64: 320401 | B64: ALUGUEIS, ARREND. E CONDOMINIOS | C64: Analitica | D64: 320401 | E64: Despesa | G64: 44872 | H64: 44872 | I64: 3204
A65: 320402 | B65: UTILIDADES | C65: Analitica | D65: 320402 | E65: Despesa | G65: 44872 | H65: 44872 | I65: 3204
A66: 320403 | B66: COMUNICACAO | C66: Analitica | D66: 320403 | E66: Despesa | G66: 44872 | H66: 44872 | I66: 3204
A67: 320404 | B67: INFORMATICA | C67: Analitica | D67: 320404 | E67: Despesa | G67: 44872 | H67: 44872 | I67: 3204
A68: 320405 | B68: PREMIO DE SEGUROS | C68: Analitica | D68: 320405 | E68: Despesa | G68: 44872 | H68: 44872 | I68: 3204
A69: 320406 | B69: MANUTENCAO E CONSERVACAO | C69: Analitica | D69: 320406 | E69: Despesa | G69: 44872 | H69: 44872 | I69: 3204
A70: 320407 | B70: VIAGENS E REPRESENTACAO | C70: Analitica | D70: 320407 | E70: Despesa | G70: 44872 | H70: 44872 | I70: 3204
A71: 320408 | B71: IMPOSTOS, MULTAS E TAXAS DIVERSAS | C71: Analitica | D71: 320408 | E71: Despesa | G71: 44872 | H71: 44872 | I71: 3204
A72: 320409 | B72: DESPESAS GERAIS | C72: Analitica | D72: 320409 | E72: Despesa | G72: 44872 | H72: 44872 | I72: 3204
A73: 3205 | B73: DEPRECIACOES E AMORTIZACOES | C73: Sintetica | D73: 3205 | E73: Despesa | G73: 44872 | H73: 44872
A74: 320501 | B74: DEPRECIACOES E AMORTIZACOES | C74: Analitica | D74: 320501 | E74: Despesa | G74: 44872 | H74: 44872 | I74: 3205
A75: 3206 | B75: CUSTOS DIRETOS OPER. PORTUµRIAS | C75: Sintetica | D75: 3206 | E75: Despesa | G75: 44872 | H75: 44872
A76: 320601001 | B76: MATERIAIS DIRETOS | C76: Analitica | D76: 320601001 | E76: Despesa | G76: 44872 | H76: 44872 | I76: 3206
A77: 320601002 | B77: TARIFAS PORTUµRIAS | C77: Analitica | D77: 320601002 | E77: Despesa | G77: 44872 | H77: 44872 | I77: 3206
A78: 3218 | B78: OUTROS CUSTOS | C78: Sintetica | D78: 3218 | E78: Despesa | G78: 44872 | H78: 44872
A79: 321801 | B79: OUTROS CUSTOS | C79: Analitica | D79: 321801 | E79: Despesa | G79: 44872 | H79: 44872 | I79: 3218
A80: 3219 | B80: ( - ) CREDITOS FISCAIS | C80: Sintetica | D80: 3219 | E80: Receita | G80: 44872 | H80: 44872
A81: 321901 | B81: ( - ) CREDITOS FISCAIS | C81: Analitica | D81: 321901 | E81: Receita | G81: 44872 | H81: 44872 | I81: 3219
A82: 3301 | B82: DESPESAS COM PESSOAL | C82: Sintetica | D82: 3301 | E82: Despesa | G82: 44872 | H82: 44872
A83: 330101 | B83: REMUNERACOES | C83: Analitica | D83: 330101 | E83: Despesa | G83: 44872 | H83: 44872 | I83: 3301
A84: 330102 | B84: ENCARGOS SOCIAIS | C84: Analitica | D84: 330102 | E84: Despesa | G84: 44872 | H84: 44872 | I84: 3301
A85: 330103 | B85: BENEFICIOS | C85: Analitica | D85: 330103 | E85: Despesa | G85: 44872 | H85: 44872 | I85: 3301
A86: 330104 | B86: OUTROS GASTOS COM PESSOAL | C86: Analitica | D86: 330104 | E86: Despesa | G86: 44872 | H86: 44872 | I86: 3301
A87: 330105 | B87: ( - ) INSS DESONERACAO | C87: Analitica | D87: 330105 | E87: Despesa | G87: 44872 | H87: 44872 | I87: 3301
A88: 3302 | B88: SERVICOS DE TERCEIROS | C88: Sintetica | D88: 3302 | E88: Despesa | G88: 44872 | H88: 44872
A89: 330201001 | B89: PJ-CONSULTORIA E ASSESSORIA | C89: Analitica | D89: 330201001 | E89: Despesa | G89: 44872 | H89: 44872 | I89: 3302
A90: 330201002 | B90: PJ-HONORARIOS ADVOCATICIOS | C90: Analitica | D90: 330201002 | E90: Despesa | G90: 44872 | H90: 44872 | I90: 3302
A91: 330201003 | B91: PJ-SEGURANCA PATRIMONIAL | C91: Analitica | D91: 330201003 | E91: Despesa | G91: 44872 | H91: 44872 | I91: 3302
A92: 330201004 | B92: PJ-LOCACAO DE MAQUINAS E EQUIPAMENTO | C92: Analitica | D92: 330201004 | E92: Despesa | G92: 44872 | H92: 44872 | I92: 3302
A93: 330201005 | B93: PJ-MAO-DE-OBRA TERCEIRIZADA | C93: Analitica | D93: 330201005 | E93: Despesa | G93: 44872 | H93: 44872 | I93: 3302
A94: 330201006 | B94: PJ-OUTROS SERVICOS CONTRATADOS-PJ | C94: Analitica | D94: 330201006 | E94: Despesa | G94: 44872 | H94: 44872 | I94: 3302
A95: 330202001 | B95: PF-CONSULTORIA E ASSESSORIA | C95: Analitica | D95: 330202001 | E95: Despesa | G95: 44872 | H95: 44872 | I95: 3302
A96: 330202003 | B96: PF-OUTROS SERVICOS CONTRATADOS-PF | C96: Analitica | D96: 330202003 | E96: Despesa | G96: 44872 | H96: 44872 | I96: 3302
A97: 3303 | B97: DESPESAS COM FROTA E EQUIPAMENTO | C97: Sintetica | D97: 3303 | E97: Despesa | G97: 44872 | H97: 44872
A98: 330301001 | B98: COMBUSTIVEIS | C98: Analitica | D98: 330301001 | E98: Despesa | G98: 44872 | H98: 44872 | I98: 3303
A99: 330301002 | B99: LUBRIFICANTES | C99: Analitica | D99: 330301002 | E99: Despesa | G99: 44872 | H99: 44872 | I99: 3303
A100: 330301003 | B100: PNEUS E RECAPAGENS | C100: Analitica | D100: 330301003 | E100: Despesa | G100: 44872 | H100: 44872 | I100: 3303
...

Sheet Base_20.12
A1: Desc_Conta | B1: CONCAT | C1: COMPETÊNCIA | D1: Valor | E1: Lote | F1: Item | G1: Data | H1: C.O. | I1: Classe | J1: Operacao | K1: Tipo | L1: Tp. Saldo | M1: Historico | N1: Unid. Medida | O1: Processo | P1: Usuario | Q1: Vlr.Lancto. | R1: Vlr.2a Moeda | S1: Vlr.3a Moeda | T1: Vlr.4a Moeda | U1: Vlr.5a Moeda | V1: Cod.Planilha | W1: Versao | X1: Centro Custo | Y1: It.Contabil | Z1: Classe Valor | AA1: Lc.Bloqueio? | AB1: Und. Orc.
A2: =IFERROR(VLOOKUP(H2,'Contas Orç'!A:B,2,0),"N/A") -> PECAS E ACESSORIOS | B2: =_xlfn.CONCAT(H2," - ",A2) -> 320301004 - PECAS E ACESSORIOS | C2: =DATE(YEAR(G2),MONTH(G2),1) -> 44866 | D2: =IF(K2="CREDITO",Q2,Q2*-1) -> 25 | E2: 0000000001 | F2: 0001 | G2: 44874 | H2: 320301004 | I2: 304 | J2: 11 | K2: Credito | L2: EM | M2: EM - PEDIDO (013491) ITEM +(0001) / (ITERRUPTOR DO NEUTRO - | O2: 000052 | P2: 000132 | Q2: 25 | R2: 0,00 | S2: 0,00 | T2: 0,00 | U2: 0,00 | V2: ORC2022 | X2: 304 | Y2: 11 | AB2: 010101
A3: =IFERROR(VLOOKUP(H3,'Contas Orç'!A:B,2,0),"N/A") -> PECAS E ACESSORIOS | B3: =_xlfn.CONCAT(H3," - ",A3) -> 330301004 - PECAS E ACESSORIOS | C3: =DATE(YEAR(G3),MONTH(G3),1) -> 44866 | D3: =IF(K3="CREDITO",Q3,Q3*-1) -> 25 | E3: 0000000001 | F3: 0002 | G3: 44874 | H3: 330301004 | I3: 201 | J3: 11 | K3: Credito | L3: EM | M3: EM - PEDIDO (013491) ITEM +(0002) / (MANCAL PARA LOCK (GUIA | O3: 000052 | P3: 000132 | Q3: 25 | R3: 0,00 | S3: 0,00 | T3: 0,00 | U3: 0,00 | V3: ORC2022 | X3: 201 | Y3: 11 | AB3: 010101
A4: =IFERROR(VLOOKUP(H4,'Contas Orç'!A:B,2,0),"N/A") -> PECAS E ACESSORIOS | B4: =_xlfn.CONCAT(H4," - ",A4) -> 320301004 - PECAS E ACESSORIOS | C4: =DATE(YEAR(G4),MONTH(G4),1) -> 44866 | D4: =IF(K4="CREDITO",Q4,Q4*-1) -> 25 | E4: 0000000002 | F4: 0001 | G4: 44874 | H4: 320301004 | I4: 304 | J4: 11 | K4: Credito | L4: RE | M4: RE - NF (909090909) P: (11150482 ) F: (000003) | O4: 000054 | P4: 000132 | Q4: 25 | R4: 0,00 | S4: 0,00 | T4: 0,00 | U4: 0,00 | X4: 304 | Y4: 11 | AB4: 010101
A5: =IFERROR(VLOOKUP(H5,'Contas Orç'!A:B,2,0),"N/A") -> PECAS E ACESSORIOS | B5: =_xlfn.CONCAT(H5," - ",A5) -> 320301004 - PECAS E ACESSORIOS | C5: =DATE(YEAR(G5),MONTH(G5),1) -> 44866 | D5: =IF(K5="CREDITO",Q5,Q5*-1) -> -25 | E5: 0000000002 | F5: 0002 | G5: 44874 | H5: 320301004 | I5: 304 | J5: 11 | K5: Debito | L5: EM | M5: EM - NF (909090909) P: (11150482 ) F: (000003) | O5: 000054 | P5: 000132 | Q5: 25 | R5: 0,00 | S5: 0,00 | T5: 0,00 | U5: 0,00 | X5: 304 | Y5: 11 | AB5: 010101
A6: =IFERROR(VLOOKUP(H6,'Contas Orç'!A:B,2,0),"N/A") -> PECAS E ACESSORIOS | B6: =_xlfn.CONCAT(H6," - ",A6) -> 330301004 - PECAS E ACESSORIOS | C6: =DATE(YEAR(G6),MONTH(G6),1) -> 44866 | D6: =IF(K6="CREDITO",Q6,Q6*-1) -> 25 | E6: 0000000002 | F6: 0003 | G6: 44874 | H6: 330301004 | I6: 201 | J6: 11 | K6: Credito | L6: RE | M6: RE - NF (909090909) P: (11010003 ) F: (000003) | O6: 000054 | P6: 000132 | Q6: 25 | R6: 0,00 | S6: 0,00 | T6: 0,00 | U6: 0,00 | X6: 201 | Y6: 11 | AB6: 010101
A7: =IFERROR(VLOOKUP(H7,'Contas Orç'!A:B,2,0),"N/A") -> PECAS E ACESSORIOS | B7: =_xlfn.CONCAT(H7," - ",A7) -> 330301004 - PECAS E ACESSORIOS | C7: =DATE(YEAR(G7),MONTH(G7),1) -> 44866 | D7: =IF(K7="CREDITO",Q7,Q7*-1) -> -25 | E7: 0000000002 | F7: 0004 | G7: 44874 | H7: 330301004 | I7: 201 | J7: 11 | K7: Debito | L7: EM | M7: EM - NF (909090909) P: (11010003 ) F: (000003) | O7: 000054 | P7: 000132 | Q7: 25 | R7: 0,00 | S7: 0,00 | T7: 0,00 | U7: 0,00 | X7: 201 | Y7: 11 | AB7: 010101
A8: =IFERROR(VLOOKUP(H8,'Contas Orç'!A:B,2,0),"N/A") -> PECAS E ACESSORIOS | B8: =_xlfn.CONCAT(H8," - ",A8) -> 320301004 - PECAS E ACESSORIOS | C8: =DATE(YEAR(G8),MONTH(G8),1) -> 44866 | D8: =IF(K8="CREDITO",Q8,Q8*-1) -> 345 | E8: 0000000003 | F8: 0001 | G8: 44876 | H8: 320301004 | I8: 301 | J8: 90 | K8: Credito | L8: EM | M8: EM - PEDIDO (000146) | (11280021 ) | F: (000361/0001) | O8: 000055 | P8: 000132 | Q8: 345 | R8: 0,00 | S8: 0,00 | T8: 0,00 | U8: 0,00 | V8: ORC2022 | Y8: 90 | AB8: 010101
A9: =IFERROR(VLOOKUP(H9,'Contas Orç'!A:B,2,0),"N/A") -> N/A | B9: =_xlfn.CONCAT(H9," - ",A9) -> - N/A | C9: =DATE(YEAR(G9),MONTH(G9),1) -> 44866 | D9: =IF(K9="CREDITO",Q9,Q9*-1) -> 170000 | E9: 0000000004 | F9: 0001 | G9: 44879 | I9: 305 | J9: 21 | K9: Credito | L9: EM | M9: EM - PEDIDO (011661) ITEM +(0001) / (EMPILHADEIRA HYSTER H50 | O9: 000055 | P9: 000044 | Q9: 170000 | R9: 0,00 | S9: 0,00 | T9: 0,00 | U9: 0,00 | X9: 305 | Y9: 21 | AB9: 010101
A10: =IFERROR(VLOOKUP(H10,'Contas Orç'!A:B,2,0),"N/A") -> N/A | B10: =_xlfn.CONCAT(H10," - ",A10) -> - N/A | C10: =DATE(YEAR(G10),MONTH(G10),1) -> 44866 | D10: =IF(K10="CREDITO",Q10,Q10*-1) -> 172000 | E10: 0000000004 | F10: 0002 | G10: 44879 | I10: 305 | J10: 21 | K10: Credito | L10: EM | M10: EM - PEDIDO (011661) ITEM +(0002) / (EMPILHADEIRA HYSTER H50 | O10: 000055 | P10: 000044 | Q10: 172000 | R10: 0,00 | S10: 0,00 | T10: 0,00 | U10: 0,00 | X10: 305 | Y10: 21 | AB10: 010101
A11: =IFERROR(VLOOKUP(H11,'Contas Orç'!A:B,2,0),"N/A") -> PJ-OUTROS SERVICOS CONTRATADOS-PJ | B11: =_xlfn.CONCAT(H11," - ",A11) -> 330201006 - PJ-OUTROS SERVICOS CONTRATADOS-PJ | C11: =DATE(YEAR(G11),MONTH(G11),1) -> 44866 | D11: =IF(K11="CREDITO",Q11,Q11*-1) -> 33809 | E11: 0000000005 | F11: 0001 | G11: 44879 | H11: 330201006 | I11: 211 | J11: 51 | K11: Credito | L11: EM | M11: EM - PEDIDO (013494) ITEM +(0001) / (SERVICO DE EMPREITADA / | O11: 000055 | P11: 000000 | Q11: 33809 | R11: 0,00 | S11: 0,00 | T11: 0,00 | U11: 0,00 | X11: 211 | Y11: 51 | AB11: 010101
A12: =IFERROR(VLOOKUP(H12,'Contas Orç'!A:B,2,0),"N/A") -> BENEFICIOS | B12: =_xlfn.CONCAT(H12," - ",A12) -> 330103 - BENEFICIOS | C12: =DATE(YEAR(G12),MONTH(G12),1) -> 44866 | D12: =IF(K12="CREDITO",Q12,Q12*-1) -> 655 | E12: 0000000007 | F12: 0001 | G12: 44879 | H12: 330103 | I12: 207 | J12: 90 | K12: Credito | L12: EM | M12: EM - PEDIDO (013492) ITEM +(0001) / (ASSISTENCIA MEDICA | O12: 000055 | P12: 000000 | Q12: 655 | R12: 0,00 | S12: 0,00 | T12: 0,00 | U12: 0,00 | X12: 207 | Y12: 90 | AB12: 010101
A13: =IFERROR(VLOOKUP(H13,'Contas Orç'!A:B,2,0),"N/A") -> BENEFICIOS | B13: =_xlfn.CONCAT(H13," - ",A13) -> 330103 - BENEFICIOS | C13: =DATE(YEAR(G13),MONTH(G13),1) -> 44866 | D13: =IF(K13="CREDITO",Q13,Q13*-1) -> 1267 | E13: 0000000007 | F13: 0002 | G13: 44879 | H13: 330103 | I13: 208 | J13: 90 | K13: Credito | L13: EM | M13: EM - PEDIDO (013492) ITEM +(0002) / (ASSISTENCIA MEDICA | O13: 000055 | P13: 000000 | Q13: 1267 | R13: 0,00 | S13: 0,00 | T13: 0,00 | U13: 0,00 | X13: 208 | Y13: 90 | AB13: 010101
A14: =IFERROR(VLOOKUP(H14,'Contas Orç'!A:B,2,0),"N/A") -> BENEFICIOS | B14: =_xlfn.CONCAT(H14," - ",A14) -> 330103 - BENEFICIOS | C14: =DATE(YEAR(G14),MONTH(G14),1) -> 44866 | D14: =IF(K14="CREDITO",Q14,Q14*-1) -> 516 | E14: 0000000007 | F14: 0003 | G14: 44879 | H14: 330103 | I14: 209 | J14: 90 | K14: Credito | L14: EM | M14: EM - PEDIDO (013492) ITEM +(0003) / (ASSISTENCIA MEDICA | O14: 000055 | P14: 000000 | Q14: 516 | R14: 0,00 | S14: 0,00 | T14: 0,00 | U14: 0,00 | X14: 209 | Y14: 90 | AB14: 010101
A15: =IFERROR(VLOOKUP(H15,'Contas Orç'!A:B,2,0),"N/A") -> BENEFICIOS | B15: =_xlfn.CONCAT(H15," - ",A15) -> 320103 - BENEFICIOS | C15: =DATE(YEAR(G15),MONTH(G15),1) -> 44866 | D15: =IF(K15="CREDITO",Q15,Q15*-1) -> 3874 | E15: 0000000007 | F15: 0004 | G15: 44879 | H15: 320103 | I15: 301 | J15: 11 | K15: Credito | L15: EM | M15: EM - PEDIDO (013492) ITEM +(0004) / (ASSISTENCIA MEDICA | O15: 000055 | P15: 000000 | Q15: 3874 | R15: 0,00 | S15: 0,00 | T15: 0,00 | U15: 0,00 | X15: 301 | Y15: 11 | AB15: 010101
A16: =IFERROR(VLOOKUP(H16,'Contas Orç'!A:B,2,0),"N/A") -> BENEFICIOS | B16: =_xlfn.CONCAT(H16," - ",A16) -> 320103 - BENEFICIOS | C16: =DATE(YEAR(G16),MONTH(G16),1) -> 44866 | D16: =IF(K16="CREDITO",Q16,Q16*-1) -> 4905 | E16: 0000000007 | F16: 0005 | G16: 44879 | H16: 320103 | I16: 302 | J16: 11 | K16: Credito | L16: EM | M16: EM - PEDIDO (013492) ITEM +(0005) / (ASSISTENCIA MEDICA | O16: 000055 | P16: 000000 | Q16: 4905 | R16: 0,00 | S16: 0,00 | T16: 0,00 | U16: 0,00 | X16: 302 | Y16: 11 | AB16: 010101
A17: =IFERROR(VLOOKUP(H17,'Contas Orç'!A:B,2,0),"N/A") -> BENEFICIOS | B17: =_xlfn.CONCAT(H17," - ",A17) -> 320103 - BENEFICIOS | C17: =DATE(YEAR(G17),MONTH(G17),1) -> 44866 | D17: =IF(K17="CREDITO",Q17,Q17*-1) -> 11568 | E17: 0000000007 | F17: 0006 | G17: 44879 | H17: 320103 | I17: 304 | J17: 21 | K17: Credito | L17: EM | M17: EM - PEDIDO (013492) ITEM +(0006) / (ASSISTENCIA MEDICA | O17: 000055 | P17: 000000 | Q17: 11568 | R17: 0,00 | S17: 0,00 | T17: 0,00 | U17: 0,00 | X17: 304 | Y17: 21 | AB17: 010101
A18: =IFERROR(VLOOKUP(H18,'Contas Orç'!A:B,2,0),"N/A") -> BENEFICIOS | B18: =_xlfn.CONCAT(H18," - ",A18) -> 320103 - BENEFICIOS | C18: =DATE(YEAR(G18),MONTH(G18),1) -> 44866 | D18: =IF(K18="CREDITO",Q18,Q18*-1) -> 608 | E18: 0000000007 | F18: 0007 | G18: 44879 | H18: 320103 | I18: 305 | J18: 33 | K18: Credito | L18: EM | M18: EM - PEDIDO (013492) ITEM +(0007) / (ASSISTENCIA MEDICA | O18: 000055 | P18: 000000 | Q18: 608 | R18: 0,00 | S18: 0,00 | T18: 0,00 | U18: 0,00 | X18: 305 | Y18: 33 | AB18: 010101
A19: =IFERROR(VLOOKUP(H19,'Contas Orç'!A:B,2,0),"N/A") -> BENEFICIOS | B19: =_xlfn.CONCAT(H19," - ",A19) -> 330103 - BENEFICIOS | C19: =DATE(YEAR(G19),MONTH(G19),1) -> 44866 | D19: =IF(K19="CREDITO",Q19,Q19*-1) -> 563 | E19: 0000000007 | F19: 0008 | G19: 44879 | H19: 330103 | I19: 206 | J19: 90 | K19: Credito | L19: EM | M19: EM - PEDIDO (013492) ITEM +(0008) / (ASSISTENCIA MEDICA | O19: 000055 | P19: 000000 | Q19: 563 | R19: 0,00 | S19: 0,00 | T19: 0,00 | U19: 0,00 | X19: 206 | Y19: 90 | AB19: 010101
A20: =IFERROR(VLOOKUP(H20,'Contas Orç'!A:B,2,0),"N/A") -> BENEFICIOS | B20: =_xlfn.CONCAT(H20," - ",A20) -> 320103 - BENEFICIOS | C20: =DATE(YEAR(G20),MONTH(G20),1) -> 44866 | D20: =IF(K20="CREDITO",Q20,Q20*-1) -> 704 | E20: 0000000007 | F20: 0009 | G20: 44879 | H20: 320103 | I20: 301 | J20: 90 | K20: Credito | L20: EM | M20: EM - PEDIDO (013492) ITEM +(0009) / (ASSISTENCIA MEDICA | O20: 000055 | P20: 000000 | Q20: 704 | R20: 0,00 | S20: 0,00 | T20: 0,00 | U20: 0,00 | X20: 301 | Y20: 90 | AB20: 010101
A21: =IFERROR(VLOOKUP(H21,'Contas Orç'!A:B,2,0),"N/A") -> BENEFICIOS | B21: =_xlfn.CONCAT(H21," - ",A21) -> 320103 - BENEFICIOS | C21: =DATE(YEAR(G21),MONTH(G21),1) -> 44866 | D21: =IF(K21="CREDITO",Q21,Q21*-1) -> 11421 | E21: 0000000007 | F21: 0010 | G21: 44879 | H21: 320103 | I21: 303 | J21: 31 | K21: Credito | L21: EM | M21: EM - PEDIDO (013492) ITEM +(0010) / (ASSISTENCIA MEDICA | O21: 000055 | P21: 000000 | Q21: 11421 | R21: 0,00 | S21: 0,00 | T21: 0,00 | U21: 0,00 | X21: 303 | Y21: 31 | AB21: 010101
A22: =IFERROR(VLOOKUP(H22,'Contas Orç'!A:B,2,0),"N/A") -> BENEFICIOS | B22: =_xlfn.CONCAT(H22," - ",A22) -> 320103 - BENEFICIOS | C22: =DATE(YEAR(G22),MONTH(G22),1) -> 44866 | D22: =IF(K22="CREDITO",Q22,Q22*-1) -> 71588 | E22: 0000000007 | F22: 0011 | G22: 44879 | H22: 320103 | I22: 305 | J22: 90 | K22: Credito | L22: EM | M22: EM - PEDIDO (013492) ITEM +(0011) / (ASSISTENCIA MEDICA | O22: 000055 | P22: 000000 | Q22: 71588 | R22: 0,00 | S22: 0,00 | T22: 0,00 | U22: 0,00 | X22: 305 | Y22: 90 | AB22: 010101
... A114: =IFERROR(VLOOKUP(H114,'Contas Orç'!A:B,2,0),"N/A") -> PJ-OUTROS SERVICOS CONTRATADOS-PJ | B114: =_xlfn.CONCAT(H114," - ",A114) -> 330201006 - PJ-OUTROS SERVICOS CONTRATADOS-PJ | C114: =DATE(YEAR(G114),MONTH(G114),1) -> 44866 | D114: =IF(K114="CREDITO",Q114,Q114*-1) -> -33809 | E114: 0000000025 | F114: 0002 | G114: 44879 | H114: 330201006 | I114: 211 | J114: 51 | K114: Debito | L114: EM | M114: EM - PED (013494) PROD: (23010001) / FOR: (ROYAL CONSTRUCOES | O114: 000054 | P114: 000132 | Q114: 33809 | R114: 0,00 | S114: 0,00 | T114: 0,00 | U114: 0,00 | X114: 211 | Y114: 51 | AB114: 010101
A115: =IFERROR(VLOOKUP(H115,'Contas Orç'!A:B,2,0),"N/A") -> N/A | B115: =_xlfn.CONCAT(H115," - ",A115) -> - N/A | C115: =DATE(YEAR(G115),MONTH(G115),1) -> 44866 | D115: =IF(K115="CREDITO",Q115,Q115*-1) -> 170000 | E115: 0000000026 | F115: 0001 | G115: 44882 | I115: 305 | J115: 21 | K115: Credito | L115: EM | M115: EM - PED (013495) PROD: (42010009) / FOR: (HYSTER YALE BRASI | O115: 000055 | P115: 000000 | Q115: 170000 | R115: 0,00 | S115: 0,00 | T115: 0,00 | U115: 0,00 | X115: 305 | Y115: 21 | AB115: 010101
A116: =IFERROR(VLOOKUP(H116,'Contas Orç'!A:B,2,0),"N/A") -> N/A | B116: =_xlfn.CONCAT(H116," - ",A116) -> - N/A | C116: =DATE(YEAR(G116),MONTH(G116),1) -> 44866 | D116: =IF(K116="CREDITO",Q116,Q116*-1) -> 172000 | E116: 0000000026 | F116: 0002 | G116: 44882 | I116: 305 | J116: 21 | K116: Credito | L116: EM | M116: EM - PED (013495) PROD: (42010008) / FOR: (HYSTER YALE BRASI | O116: 000055 | P116: 000000 | Q116: 172000 | R116: 0,00 | S116: 0,00 | T116: 0,00 | U116: 0,00 | X116: 305 | Y116: 21 | AB116: 010101
A117: =IFERROR(VLOOKUP(H117,'Contas Orç'!A:B,2,0),"N/A") -> COMBUSTIVEIS | B117: =_xlfn.CONCAT(H117," - ",A117) -> 330301001 - COMBUSTIVEIS | C117: =DATE(YEAR(G117),MONTH(G117),1) -> 44866 | D117: =IF(K117="CREDITO",Q117,Q117*-1) -> 64090 | E117: 0000000027 | F117: 0001 | G117: 44882 | H117: 330301001 | I117: 209 | J117: 11 | K117: Credito | L117: EM | M117: EM - PED (013496) PROD: (11100008) / FOR: (PETROTUDO COMERCI | O117: 000055 | P117: 000000 | Q117: 64090 | R117: 0,00 | S117: 0,00 | T117: 0,00 | U117: 0,00 | X117: 209 | Y117: 11 | AB117: 010101
A118: =IFERROR(VLOOKUP(H118,'Contas Orç'!A:B,2,0),"N/A") -> COMBUSTIVEIS | B118: =_xlfn.CONCAT(H118," - ",A118) -> 330301001 - COMBUSTIVEIS | C118: =DATE(YEAR(G118),MONTH(G118),1) -> 44866 | D118: =IF(K118="CREDITO",Q118,Q118*-1) -> 64090 | E118: 0000000027 | F118: 0002 | G118: 44882 | H118: 330301001 | I118: 209 | J118: 21 | K118: Credito | L118: EM | M118: EM - PED (013496) PROD: (11100008) / FOR: (PETROTUDO COMERCI | O118: 000055 | P118: 000000 | Q118: 64090 | R118: 0,00 | S118: 0,00 | T118: 0,00 | U118: 0,00 | X118: 209 | Y118: 21 | AB118: 010101
A119: =IFERROR(VLOOKUP(H119,'Contas Orç'!A:B,2,0),"N/A") -> PECAS E ACESSORIOS | B119: =_xlfn.CONCAT(H119," - ",A119) -> 320301004 - PECAS E ACESSORIOS | C119: =DATE(YEAR(G119),MONTH(G119),1) -> 44866 | D119: =IF(K119="CREDITO",Q119,Q119*-1) -> 398 | E119: 0000000028 | F119: 0001 | G119: 44882 | H119: 320301004 | I119: 304 | J119: 11 | K119: Credito | L119: EM | M119: EM - PED (013500) PROD: (22010002) / FOR: (FREIO DIESEL PECA | O119: 000055 | P119: 000000 | Q119: 398 | R119: 0,00 | S119: 0,00 | T119: 0,00 | U119: 0,00 | X119: 304 | Y119: 11 | AB119: 010101
A120: =IFERROR(VLOOKUP(H120,'Contas Orç'!A:B,2,0),"N/A") -> PJ-OUTROS SERVICOS CONTRATADOS-PJ | B120: =_xlfn.CONCAT(H120," - ",A120) -> 330201006 - PJ-OUTROS SERVICOS CONTRATADOS-PJ | C120: =DATE(YEAR(G120),MONTH(G120),1) -> 44866 | D120: =IF(K120="CREDITO",Q120,Q120*-1) -> 499 | E120: 0000000029 | F120: 0001 | G120: 44882 | H120: 330201006 | I120: 201 | J120: 90 | K120: Credito | L120: EM | M120: EM - PED (013499) PROD: (23010016) / FOR: (APROVADOR SISTEMA | O120: 000055 | P120: 000000 | Q120: 499 | R120: 0,00 | S120: 0,00 | T120: 0,00 | U120: 0,00 | X120: 201 | Y120: 90 | AB120: 010101
A121: =IFERROR(VLOOKUP(H121,'Contas Orç'!A:B,2,0),"N/A") -> PJ-OUTROS SERVICOS CONTRATADOS-PJ | B121: =_xlfn.CONCAT(H121," - ",A121) -> 330201006 - PJ-OUTROS SERVICOS CONTRATADOS-PJ | C121: =DATE(YEAR(G121),MONTH(G121),1) -> 44866 | D121: =IF(K121="CREDITO",Q121,Q121*-1) -> 499 | E121: 0000000029 | F121: 0002 | G121: 44882 | H121: 330201006 | I121: 201 | J121: 90 | K121: Credito | L121: EM | M121: EM - PED (013499) PROD: (23010016) / FOR: (APROVADOR SISTEMA | O121: 000055 | P121: 000000 | Q121: 499 | R121: 0,00 | S121: 0,00 | T121: 0,00 | U121: 0,00 | X121: 201 | Y121: 90 | AB121: 010101
A122: =IFERROR(VLOOKUP(H122,'Contas Orç'!A:B,2,0),"N/A") -> PJ-OUTROS SERVICOS CONTRATADOS-PJ | B122: =_xlfn.CONCAT(H122," - ",A122) -> 330201006 - PJ-OUTROS SERVICOS CONTRATADOS-PJ | C122: =DATE(YEAR(G122),MONTH(G122),1) -> 44866 | D122: =IF(K122="CREDITO",Q122,Q122*-1) -> 499 | E122: 0000000029 | F122: 0003 | G122: 44882 | H122: 330201006 | I122: 201 | J122: 90 | K122: Credito | L122: EM | M122: EM - PED (013499) PROD: (23010016) / FOR: (APROVADOR SISTEMA | O122: 000055 | P122: 000000 | Q122: 499 | R122: 0,00 | S122: 0,00 | T122: 0,00 | U122: 0,00 | X122: 201 | Y122: 90 | AB122: 010101
A123: =IFERROR(VLOOKUP(H123,'Contas Orç'!A:B,2,0),"N/A") -> PJ-OUTROS SERVICOS CONTRATADOS-PJ | B123: =_xlfn.CONCAT(H123," - ",A123) -> 330201006 - PJ-OUTROS SERVICOS CONTRATADOS-PJ | C123: =DATE(YEAR(G123),MONTH(G123),1) -> 44866 | D123: =IF(K123="CREDITO",Q123,Q123*-1) -> 499 | E123: 0000000029 | F123: 0004 | G123: 44882 | H123: 330201006 | I123: 201 | J123: 90 | K123: Credito | L123: EM | M123: EM - PED (013499) PROD: (23010016) / FOR: (APROVADOR SISTEMA | O123: 000055 | P123: 000000 | Q123: 499 | R123: 0,00 | S123: 0,00 | T123: 0,00 | U123: 0,00 | X123: 201 | Y123: 90 | AB123: 010101
A124: =IFERROR(VLOOKUP(H124,'Contas Orç'!A:B,2,0),"N/A") -> PJ-OUTROS SERVICOS CONTRATADOS-PJ | B124: =_xlfn.CONCAT(H124," - ",A124) -> 330201006 - PJ-OUTROS SERVICOS CONTRATADOS-PJ | C124: =DATE(YEAR(G124),MONTH(G124),1) -> 44866 | D124: =IF(K124="CREDITO",Q124,Q124*-1) -> 499 | E124: 0000000029 | F124: 0005 | G124: 44882 | H124: 330201006 | I124: 201 | J124: 90 | K124: Credito | L124: EM | M124: EM - PED (013499) PROD: (23010016) / FOR: (APROVADOR SISTEMA | O124: 000055 | P124: 000000 | Q124: 499 | R124: 0,00 | S124: 0,00 | T124: 0,00 | U124: 0,00 | X124: 201 | Y124: 90 | AB124: 010101
A125: =IFERROR(VLOOKUP(H125,'Contas Orç'!A:B,2,0),"N/A") -> PJ-OUTROS SERVICOS CONTRATADOS-PJ | B125: =_xlfn.CONCAT(H125," - ",A125) -> 330201006 - PJ-OUTROS SERVICOS CONTRATADOS-PJ | C125: =DATE(YEAR(G125),MONTH(G125),1) -> 44866 | D125: =IF(K125="CREDITO",Q125,Q125*-1) -> 499 | E125: 0000000029 | F125: 0006 | G125: 44882 | H125: 330201006 | I125: 201 | J125: 90 | K125: Credito | L125: EM | M125: EM - PED (013499) PROD: (23010016) / FOR: (APROVADOR SISTEMA | O125: 000055 | P125: 000000 | Q125: 499 | R125: 0,00 | S125: 0,00 | T125: 0,00 | U125: 0,00 | X125: 201 | Y125: 90 | AB125: 010101
A126: =IFERROR(VLOOKUP(H126,'Contas Orç'!A:B,2,0),"N/A") -> PJ-LOCACAO DE MAQUINAS E EQUIPAMENTO | B126: =_xlfn.CONCAT(H126," - ",A126) -> 320201004 - PJ-LOCACAO DE MAQUINAS E EQUIPAMENTO | C126: =DATE(YEAR(G126),MONTH(G126),1) -> 44866 | D126: =IF(K126="CREDITO",Q126,Q126*-1) -> 3631 | E126: 0000000030 | F126: 0001 | G126: 44882 | H126: 320201004 | I126: 301 | J126: 90 | K126: Credito | L126: EM | M126: EM - PED (013498) PROD: (23010005) / FOR: (COMPANHIA DE LOCA | O126: 000055 | P126: 000000 | Q126: 3631 | R126: 0,00 | S126: 0,00 | T126: 0,00 | U126: 0,00 | X126: 301 | Y126: 90 | AB126: 010101
A127: =IFERROR(VLOOKUP(H127,'Contas Orç'!A:B,2,0),"N/A") -> PJ-LOCACAO DE MAQUINAS E EQUIPAMENTO | B127: =_xlfn.CONCAT(H127," - ",A127) -> 320201004 - PJ-LOCACAO DE MAQUINAS E EQUIPAMENTO | C127: =DATE(YEAR(G127),MONTH(G127),1) -> 44866 | D127: =IF(K127="CREDITO",Q127,Q127*-1) -> 3701 | E127: 0000000030 | F127: 0002 | G127: 44882 | H127: 320201004 | I127: 301 | J127: 90 | K127: Credito | L127: EM | M127: EM - PED (013498) PROD: (23010005) / FOR: (COMPANHIA DE LOCA | O127: 000055 | P127: 000000 | Q127: 3701 | R127: 0,00 | S127: 0,00 | T127: 0,00 | U127: 0,00 | X127: 301 | Y127: 90 | AB127: 010101
A128: =IFERROR(VLOOKUP(H128,'Contas Orç'!A:B,2,0),"N/A") -> PJ-LOCACAO DE MAQUINAS E EQUIPAMENTO | B128: =_xlfn.CONCAT(H128," - ",A128) -> 320201004 - PJ-LOCACAO DE MAQUINAS E EQUIPAMENTO | C128: =DATE(YEAR(G128),MONTH(G128),1) -> 44866 | D128: =IF(K128="CREDITO",Q128,Q128*-1) -> 1885 | E128: 0000000030 | F128: 0003 | G128: 44882 | H128: 320201004 | I128: 301 | J128: 90 | K128: Credito | L128: EM | M128: EM - PED (013498) PROD: (23010005) / FOR: (COMPANHIA DE LOCA | O128: 000055 | P128: 000000 | Q128: 1885 | R128: 0,00 | S128: 0,00 | T128: 0,00 | U128: 0,00 | X128: 301 | Y128: 90 | AB128: 010101
... A260: =IFERROR(VLOOKUP(H260,'Contas Orç'!A:B,2,0),"N/A") -> PJ-OUTROS SERVICOS CONTRATADOS-PJ | B260: =_xlfn.CONCAT(H260," - ",A260) -> 330201006 - PJ-OUTROS SERVICOS CONTRATADOS-PJ | C260: =DATE(YEAR(G260),MONTH(G260),1) -> 44866 | D260: =IF(K260="CREDITO",Q260,Q260*-1) -> -586.34 | E260: 0000000077 | F260: 0002 | G260: 44886 | H260: 330201006 | I260: 201 | J260: 90 | K260: Debito | L260: EM | M260: EM - PED (013507) PROD: (23010006) / FOR: (BERNUTTY TECHNOLO | O260: 000054 | P260: 000070 | Q260: 586.34 | R260: 0,00 | S260: 0,00 | T260: 0,00 | U260: 0,00 | X260: 201 | Y260: 90 | AB260: 010101
A261: =IFERROR(VLOOKUP(H261,'Contas Orç'!A:B,2,0),"N/A") -> RECEITA BRUTA DE TRANSPORTES | B261: =_xlfn.CONCAT(H261," - ",A261) -> 310101 - RECEITA BRUTA DE TRANSPORTES | C261: =DATE(YEAR(G261),MONTH(G261),1) -> 44866 | D261: =IF(K261="CREDITO",Q261,Q261*-1) -> 1582.57 | E261: 0000000078 | F261: 0001 | G261: 44888 | H261: 310101 | I261: 304 | J261: 11 | K261: Credito | L261: RE | M261: RE - NF (000053700) P: (21010001) C: (HAMBURG SUD A/S) | O261: 000101 | P261: 000132 | Q261: 1582.57 | R261: 0,00 | S261: 0,00 | T261: 0,00 | U261: 0,00 | V261: ORC2022_2 | X261: 304 | Y261: 11 | AB261: 010101
A262: =IFERROR(VLOOKUP(H262,'Contas Orç'!A:B,2,0),"N/A") -> IMOBILIZADO EM ANDAMENTO - PROPRIOS | B262: =_xlfn.CONCAT(H262," - ",A262) -> 120307001 - IMOBILIZADO EM ANDAMENTO - PROPRIOS | C262: =DATE(YEAR(G262),MONTH(G262),1) -> 44866 | D262: =IF(K262="CREDITO",Q262,Q262*-1) -> 241.77 | E262: 0000000079 | F262: 0001 | G262: 44888 | H262: 120307001 | I262: 211 | J262: 51 | K262: Credito | L262: EM | M262: EM - PED (013508) PROD: (11100029) / FOR: (POSTO PECEM COMER | O262: 000055 | P262: 000000 | Q262: 241.77 | R262: 0,00 | S262: 0,00 | T262: 0,00 | U262: 0,00 | V262: ORC2022_2 | X262: 211 | Y262: 51 | AB262: 010101
A263: =IFERROR(VLOOKUP(H263,'Contas Orç'!A:B,2,0),"N/A") -> IMOBILIZADO EM ANDAMENTO - PROPRIOS | B263: =_xlfn.CONCAT(H263," - ",A263) -> 120307001 - IMOBILIZADO EM ANDAMENTO - PROPRIOS | C263: =DATE(YEAR(G263),MONTH(G263),1) -> 44866 | D263: =IF(K263="CREDITO",Q263,Q263*-1) -> 1278.34 | E263: 0000000079 | F263: 0002 | G263: 44888 | H263: 120307001 | I263: 211 | J263: 51 | K263: Credito | L263: EM | M263: EM - PED (013508) PROD: (11100029) / FOR: (POSTO PECEM COMER | O263: 000055 | P263: 000000 | Q263: 1278.34 | R263: 0,00 | S263: 0,00 | T263: 0,00 | U263: 0,00 | V263: ORC2022_2 | X263: 211 | Y263: 51 | AB263: 010101
A264: =IFERROR(VLOOKUP(H264,'Contas Orç'!A:B,2,0),"N/A") -> IMOBILIZADO EM ANDAMENTO - PROPRIOS | B264: =_xlfn.CONCAT(H264," - ",A264) -> 120307001 - IMOBILIZADO EM ANDAMENTO - PROPRIOS | C264: =DATE(YEAR(G264),MONTH(G264),1) -> 44866 | D264: =IF(K264="CREDITO",Q264,Q264*-1) -> 291.2 | E264: 0000000079 | F264: 0003 | G264: 44888 | H264: 120307001 | I264: 211 | J264: 51 | K264: Credito | L264: EM | M264: EM - PED (013508) PROD: (11100008) / FOR: (POSTO PECEM COMER | O264: 000055 | P264: 000000 | Q264: 291.2 | R264: 0,00 | S264: 0,00 | T264: 0,00 | U264: 0,00 | V264: ORC2022_2 | X264: 211 | Y264: 51 | AB264: 010101
A265: =IFERROR(VLOOKUP(H265,'Contas Orç'!A:B,2,0),"N/A") -> IMOBILIZADO EM ANDAMENTO - PROPRIOS | B265: =_xlfn.CONCAT(H265," - ",A265) -> 120307001 - IMOBILIZADO EM ANDAMENTO - PROPRIOS | C265: =DATE(YEAR(G265),MONTH(G265),1) -> 44866 | D265: =IF(K265="CREDITO",Q265,Q265*-1) -> 49.92 | E265: 0000000079 | F265: 0004 | G265: 44888 | H265: 120307001 | I265: 211 | J265: 51 | K265: Credito | L265: EM | M265: EM - PED (013508) PROD: (11100029) / FOR: (POSTO PECEM COMER | O265: 000055 | P265: 000000 | Q265: 49.92 | R265: 0,00 | S265: 0,00 | T265: 0,00 | U265: 0,00 | V265: ORC2022_2 | X265: 211 | Y265: 51 | AB265: 010101
A266: =IFERROR(VLOOKUP(H266,'Contas Orç'!A:B,2,0),"N/A") -> IMOBILIZADO EM ANDAMENTO - PROPRIOS | B266: =_xlfn.CONCAT(H266," - ",A266) -> 120307001 - IMOBILIZADO EM ANDAMENTO - PROPRIOS | C266: =DATE(YEAR(G266),MONTH(G266),1) -> 44866 | D266: =IF(K266="CREDITO",Q266,Q266*-1) -> 205.59 | E266: 0000000079 | F266: 0005 | G266: 44888 | H266: 120307001 | I266: 211 | J266: 51 | K266: Credito | L266: EM | M266: EM - PED (013508) PROD: (11100032) / FOR: (POSTO PECEM COMER | O266: 000055 | P266: 000000 | Q266: 205.59 | R266: 0,00 | S266: 0,00 | T266: 0,00 | U266: 0,00 | V266: ORC2022_2 | X266: 211 | Y266: 51 | AB266: 010101
A267: =IFERROR(VLOOKUP(H267,'Contas Orç'!A:B,2,0),"N/A") -> IMOBILIZADO EM ANDAMENTO - PROPRIOS | B267: =_xlfn.CONCAT(H267," - ",A267) -> 120307001 - IMOBILIZADO EM ANDAMENTO - PROPRIOS | C267: =DATE(YEAR(G267),MONTH(G267),1) -> 44866 | D267: =IF(K267="CREDITO",Q267,Q267*-1) -> 49.9 | E267: 0000000079 | F267: 0006 | G267: 44888 | H267: 120307001 | I267: 211 | J267: 51 | K267: Credito | L267: EM | M267: EM - PED (013508) PROD: (11100032) / FOR: (POSTO PECEM COMER | O267: 000055 | P267: 000000 | Q267: 49.9 | R267: 0,00 | S267: 0,00 | T267: 0,00 | U267: 0,00 | V267: ORC2022_2 | X267: 211 | Y267: 51 | AB267: 010101
A268: =IFERROR(VLOOKUP(H268,'Contas Orç'!A:B,2,0),"N/A") -> IMOBILIZADO EM ANDAMENTO - PROPRIOS | B268: =_xlfn.CONCAT(H268," - ",A268) -> 120307001 - IMOBILIZADO EM ANDAMENTO - PROPRIOS | C268: =DATE(YEAR(G268),MONTH(G268),1) -> 44866 | D268: =IF(K268="CREDITO",Q268,Q268*-1) -> 20924.58 | E268: 0000000080 | F268: 0001 | G268: 44888 | H268: 120307001 | I268: 211 | J268: 51 | K268: Credito | L268: EM | M268: EM - PED (013509) PROD: (23010001) / FOR: (EJR CONSTRUCOES E | O268: 000055 | P268: 000000 | Q268: 20924.58 | R268: 0,00 | S268: 0,00 | T268: 0,00 | U268: 0,00 | V268: ORC2022_2 | X268: 211 | Y268: 51 | AB268: 010101
A269: =IFERROR(VLOOKUP(H269,'Contas Orç'!A:B,2,0),"N/A") -> MOVEIS E UTENSILIOS | B269: =_xlfn.CONCAT(H269," - ",A269) -> 120302001 - MOVEIS E UTENSILIOS | C269: =DATE(YEAR(G269),MONTH(G269),1) -> 44866 | D269: =IF(K269="CREDITO",Q269,Q269*-1) -> 3482.58 | E269: 0000000083 | F269: 0001 | G269: 44888 | H269: 120302001 | I269: 305 | J269: 21 | K269: Credito | L269: EM | M269: EM - PED (013511) PROD: (44010033) / FOR: (REFRIGERACAO DUFR | O269: 000055 | P269: 000000 | Q269: 3482.58 | R269: 0,00 | S269: 0,00 | T269: 0,00 | U269: 0,00 | V269: ORC2022_2 | X269: 305 | Y269: 21 | AB269: 010101
A270: =IFERROR(VLOOKUP(H270,'Contas Orç'!A:B,2,0),"N/A") -> IMOBILIZADO EM ANDAMENTO - PROPRIOS | B270: =_xlfn.CONCAT(H270," - ",A270) -> 120307001 - IMOBILIZADO EM ANDAMENTO - PROPRIOS | C270: =DATE(YEAR(G270),MONTH(G270),1) -> 44866 | D270: =IF(K270="CREDITO",Q270,Q270*-1) -> 1568.88 | E270: 0000000087 | F270: 0001 | G270: 44888 | H270: 120307001 | I270: 211 | J270: 51 | K270: Credito | L270: EM | M270: EM - PED (013510) PROD: (12060015) / FOR: (PEDREIRA ITATIBA | O270: 000055 | P270: 000000 | Q270: 1568.88 | R270: 0,00 | S270: 0,00 | T270: 0,00 | U270: 0,00 | V270: ORC2022_2 | X270: 211 | Y270: 51 | AB270: 010101
A271: =IFERROR(VLOOKUP(H271,'Contas Orç'!A:B,2,0),"N/A") -> MOVEIS E UTENSILIOS | B271: =_xlfn.CONCAT(H271," - ",A271) -> 120302001 - MOVEIS E UTENSILIOS | C271: =DATE(YEAR(G271),MONTH(G271),1) -> 44866 | D271: =IF(K271="CREDITO",Q271,Q271*-1) -> 2090 | E271: 0000000088 | F271: 0001 | G271: 44888 | H271: 120302001 | I271: 301 | J271: 90 | K271: Credito | L271: EM | M271: EM - PED (013512) PROD: (44010008) / FOR: (M. F. U. DE OLIVE | O271: 000055 | P271: 000000 | Q271: 2090 | R271: 0,00 | S271: 0,00 | T271: 0,00 | U271: 0,00 | V271: ORC2022_2 | X271: 301 | Y271: 90 | AB271: 010101
A272: =IFERROR(VLOOKUP(H272,'Contas Orç'!A:B,2,0),"N/A") -> RECEITA BRUTA DE TRANSPORTES | B272: =_xlfn.CONCAT(H272," - ",A272) -> 310101 - RECEITA BRUTA DE TRANSPORTES | C272: =DATE(YEAR(G272),MONTH(G272),1) -> 44866 | D272: =IF(K272="CREDITO",Q272,Q272*-1) -> 1710.82 | E272: 0000000093 | F272: 0001 | G272: 44888 | H272: 310101 | I272: 304 | J272: 11 | K272: Credito | L272: RE | M272: RE - NF (000053701) P: (21010001) C: (HAMBURG SUD A/S) | O272: 000101 | P272: 000032 | Q272: 1710.82 | R272: 0,00 | S272: 0,00 | T272: 0,00 | U272: 0,00 | V272: ORC2022_2 | X272: 304 | Y272: 11 | AB272: 010101
... A338: =IFERROR(VLOOKUP(H338,'Contas Orç'!A:B,2,0),"N/A") -> PNEUS E RECAPAGENS | B338: =_xlfn.CONCAT(H338," - ",A338) -> 320301003 - PNEUS E RECAPAGENS | C338: =DATE(YEAR(G338),MONTH(G338),1) -> 44866 | D338: =IF(K338="CREDITO",Q338,Q338*-1) -> 33250.02 | E338: 0000000119 | F338: 0001 | G338: 44893 | H338: 320301003 | I338: 304 | J338: 11 | K338: Credito | L338: EM | M338: EM - PED (013513) PROD: (11300002) / FOR: (PNEUBRAS COMERCIO | O338: 000055 | P338: 000000 | Q338: 33250.02 | R338: 0,00 | S338: 0,00 | T338: 0,00 | U338: 0,00 | V338: ORC2022_2 | X338: 304 | Y338: 11 | AB338: 010101
A339: =IFERROR(VLOOKUP(H339,'Contas Orç'!A:B,2,0),"N/A") -> BENEFICIOS | B339: =_xlfn.CONCAT(H339," - ",A339) -> 320103 - BENEFICIOS | C339: =DATE(YEAR(G339),MONTH(G339),1) -> 44866 | D339: =IF(K339="CREDITO",Q339,Q339*-1) -> -3873.69 | E339: 0000000120 | F339: 0001 | G339: 44879 | H339: 320103 | I339: 301 | K339: Debito | L339: RE | M339: RE - HIST CF.1933 -23010009-VR NF.041577496-HAPVID | O339: 000082 | P339: 000074 | Q339: 3873.69 | R339: 0,00 | S339: 0,00 | T339: 0,00 | U339: 0,00 | V339: ORC2022_2 | X339: 301 | Y339: 11 | AB339: 010101
A340: =IFERROR(VLOOKUP(H340,'Contas Orç'!A:B,2,0),"N/A") -> BENEFICIOS | B340: =_xlfn.CONCAT(H340," - ",A340) -> 320103 - BENEFICIOS | C340: =DATE(YEAR(G340),MONTH(G340),1) -> 44866 | D340: =IF(K340="CREDITO",Q340,Q340*-1) -> -4905.34 | E340: 0000000120 | F340: 0002 | G340: 44879 | H340: 320103 | I340: 302 | K340: Debito | L340: RE | M340: RE - HIST CF.1933 -23010009-VR NF.041577496-HAPVID | O340: 000082 | P340: 000074 | Q340: 4905.34 | R340: 0,00 | S340: 0,00 | T340: 0,00 | U340: 0,00 | V340: ORC2022_2 | X340: 302 | Y340: 11 | AB340: 010101
A341: =IFERROR(VLOOKUP(H341,'Contas Orç'!A:B,2,0),"N/A") -> BENEFICIOS | B341: =_xlfn.CONCAT(H341," - ",A341) -> 320103 - BENEFICIOS | C341: =DATE(YEAR(G341),MONTH(G341),1) -> 44866 | D341: =IF(K341="CREDITO",Q341,Q341*-1) -> -11568.48 | E341: 0000000120 | F341: 0003 | G341: 44879 | H341: 320103 | I341: 304 | K341: Debito | L341: RE | M341: RE - HIST CF.1933 -23010009-VR NF.041577496-HAPVID | O341: 000082 | P341: 000074 | Q341: 11568.48 | R341: 0,00 | S341: 0,00 | T341: 0,00 | U341: 0,00 | V341: ORC2022_2 | X341: 304 | Y341: 21 | AB341: 010101
A342: =IFERROR(VLOOKUP(H342,'Contas Orç'!A:B,2,0),"N/A") -> BENEFICIOS | B342: =_xlfn.CONCAT(H342," - ",A342) -> 320103 - BENEFICIOS | C342: =DATE(YEAR(G342),MONTH(G342),1) -> 44866 | D342: =IF(K342="CREDITO",Q342,Q342*-1) -> -607.83 | E342: 0000000120 | F342: 0004 | G342: 44879 | H342: 320103 | I342: 305 | K342: Debito | L342: RE | M342: RE - HIST CF.1933 -23010009-VR NF.041577496-HAPVID | O342: 000082 | P342: 000074 | Q342: 607.83 | R342: 0,00 | S342: 0,00 | T342: 0,00 | U342: 0,00 | V342: ORC2022_2 | X342: 305 | Y342: 33 | AB342: 010101
A343: =IFERROR(VLOOKUP(H343,'Contas Orç'!A:B,2,0),"N/A") -> BENEFICIOS | B343: =_xlfn.CONCAT(H343," - ",A343) -> 320103 - BENEFICIOS | C343: =DATE(YEAR(G343),MONTH(G343),1) -> 44866 | D343: =IF(K343="CREDITO",Q343,Q343*-1) -> -704.05 | E343: 0000000120 | F343: 0005 | G343: 44879 | H343: 320103 | I343: 301 | K343: Debito | L343: RE | M343: RE - HIST CF.1933 -23010009-VR NF.041577496-HAPVID | O343: 000082 | P343: 000074 | Q343: 704.05 | R343: 0,00 | S343: 0,00 | T343: 0,00 | U343: 0,00 | V343: ORC2022_2 | X343: 301 | Y343: 90 | AB343: 010101
A344: =IFERROR(VLOOKUP(H344,'Contas Orç'!A:B,2,0),"N/A") -> BENEFICIOS | B344: =_xlfn.CONCAT(H344," - ",A344) -> 320103 - BENEFICIOS | C344: =DATE(YEAR(G344),MONTH(G344),1) -> 44866 | D344: =IF(K344="CREDITO",Q344,Q344*-1) -> -11421.09 | E344: 0000000120 | F344: 0006 | G344: 44879 | H344: 320103 | I344: 303 | K344: Debito | L344: RE | M344: RE - HIST CF.1933 -23010009-VR NF.041577496-HAPVID | O344: 000082 | P344: 000074 | Q344: 11421.09 | R344: 0,00 | S344: 0,00 | T344: 0,00 | U344: 0,00 | V344: ORC2022_2 | X344: 303 | Y344: 31 | AB344: 010101
A345: =IFERROR(VLOOKUP(H345,'Contas Orç'!A:B,2,0),"N/A") -> BENEFICIOS | B345: =_xlfn.CONCAT(H345," - ",A345) -> 320103 - BENEFICIOS | C345: =DATE(YEAR(G345),MONTH(G345),1) -> 44866 | D345: =IF(K345="CREDITO",Q345,Q345*-1) -> -71587.85 | E345: 0000000120 | F345: 0007 | G345: 44879 | H345: 320103 | I345: 305 | K345: Debito | L345: RE | M345: RE - HIST CF.1933 -23010009-VR NF.041577496-HAPVID | O345: 000082 | P345: 000074 | Q345: 71587.85 | R345: 0,00 | S345: 0,00 | T345: 0,00 | U345: 0,00 | V345: ORC2022_2 | X345: 305 | Y345: 90 | AB345: 010101
A346: =IFERROR(VLOOKUP(H346,'Contas Orç'!A:B,2,0),"N/A") -> BENEFICIOS | B346: =_xlfn.CONCAT(H346," - ",A346) -> 320103 - BENEFICIOS | C346: =DATE(YEAR(G346),MONTH(G346),1) -> 44866 | D346: =IF(K346="CREDITO",Q346,Q346*-1) -> -4154.35 | E346: 0000000120 | F346: 0008 | G346: 44879 | H346: 320103 | I346: 305 | K346: Debito | L346: RE | M346: RE - HIST CF.1933 -23010009-VR NF.041577496-HAPVID | O346: 000082 | P346: 000074 | Q346: 4154.35 | R346: 0,00 | S346: 0,00 | T346: 0,00 | U346: 0,00 | V346: ORC2022_2 | X346: 306 | Y346: 90 | AB346: 010101
A347: =IFERROR(VLOOKUP(H347,'Contas Orç'!A:B,2,0),"N/A") -> REMUNERACOES | B347: =_xlfn.CONCAT(H347," - ",A347) -> 320101 - REMUNERACOES | C347: =DATE(YEAR(G347),MONTH(G347),1) -> 44866 | D347: =IF(K347="CREDITO",Q347,Q347*-1) -> -9.99 | E347: 0000000121 | F347: 0001 | G347: 44895 | H347: 320101 | J347: 90 | K347: Debito | L347: RE | M347: RE - HIST TESTE PCO | O347: 000082 | P347: 000098 | Q347: 9.99 | R347: 0,00 | S347: 0,00 | T347: 0,00 | U347: 0,00 | V347: ORC2022_2 | X347: 201 | Y347: 90 | AB347: 010101
A348: =IFERROR(VLOOKUP(H348,'Contas Orç'!A:B,2,0),"N/A") -> BENEFICIOS | B348: =_xlfn.CONCAT(H348," - ",A348) -> 320103 - BENEFICIOS | C348: =DATE(YEAR(G348),MONTH(G348),1) -> 44866 | D348: =IF(K348="CREDITO",Q348,Q348*-1) -> -4014.5 | E348: 0000000122 | F348: 0001 | G348: 44886 | H348: 320103 | I348: 301 | K348: Debito | L348: RE | M348: RE - HIST CF.1933 -23010009-VR NF.413470308-HAPVID | O348: 000082 | P348: 000074 | Q348: 4014.5 | R348: 0,00 | S348: 0,00 | T348: 0,00 | U348: 0,00 | V348: ORC2022_2 | X348: 301 | Y348: 11 | AB348: 010101
A349: =IFERROR(VLOOKUP(H349,'Contas Orç'!A:B,2,0),"N/A") -> BENEFICIOS | B349: =_xlfn.CONCAT(H349," - ",A349) -> 320103 - BENEFICIOS | C349: =DATE(YEAR(G349),MONTH(G349),1) -> 44866 | D349: =IF(K349="CREDITO",Q349,Q349*-1) -> -4764.53 | E349: 0000000122 | F349: 0002 | G349: 44886 | H349: 320103 | I349: 302 | K349: Debito | L349: RE | M349: RE - HIST CF.1933 -23010009-VR NF.413470308-HAPVID | O349: 000082 | P349: 000074 | Q349: 4764.53 | R349: 0,00 | S349: 0,00 | T349: 0,00 | U349: 0,00 | V349: ORC2022_2 | X349: 302 | Y349: 11 | AB349: 010101
A350: =IFERROR(VLOOKUP(H350,'Contas Orç'!A:B,2,0),"N/A") -> BENEFICIOS | B350: =_xlfn.CONCAT(H350," - ",A350) -> 320103 - BENEFICIOS | C350: =DATE(YEAR(G350),MONTH(G350),1) -> 44866 | D350: =IF(K350="CREDITO",Q350,Q350*-1) -> -12176.31 | E350: 0000000122 | F350: 0003 | G350: 44886 | H350: 320103 | I350: 304 | K350: Debito | L350: RE | M350: RE - HIST CF.1933 -23010009-VR NF.413470308-HAPVID | O350: 000082 | P350: 000074 | Q350: 12176.31 | R350: 0,00 | S350: 0,00 | T350: 0,00 | U350: 0,00 | V350: ORC2022_2 | X350: 304 | Y350: 21 | AB350: 010101
A351: =IFERROR(VLOOKUP(H351,'Contas Orç'!A:B,2,0),"N/A") -> BENEFICIOS | B351: =_xlfn.CONCAT(H351," - ",A351) -> 320103 - BENEFICIOS | C351: =DATE(YEAR(G351),MONTH(G351),1) -> 44866 | D351: =IF(K351="CREDITO",Q351,Q351*-1) -> -607.83 | E351: 0000000122 | F351: 0004 | G351: 44886 | H351: 320103 | I351: 305 | K351: Debito | L351: RE | M351: RE - HIST CF.1933 -23010009-VR NF.413470308-HAPVID | O351: 000082 | P351: 000074 | Q351: 607.83 | R351: 0,00 | S351: 0,00 | T351: 0,00 | U351: 0,00 | V351: ORC2022_2 | X351: 305 | Y351: 33 | AB351: 010101
A352: =IFERROR(VLOOKUP(H352,'Contas Orç'!A:B,2,0),"N/A") -> BENEFICIOS | B352: =_xlfn.CONCAT(H352," - ",A352) -> 320103 - BENEFICIOS | C352: =DATE(YEAR(G352),MONTH(G352),1) -> 44866 | D352: =IF(K352="CREDITO",Q352,Q352*-1) -> -833.61 | E352: 0000000122 | F352: 0005 | G352: 44886 | H352: 320103 | I352: 301 | K352: Debito | L352: RE | M352: RE - HIST CF.1933 -23010009-VR NF.413470308-HAPVID | O352: 000082 | P352: 000074 | Q352: 833.61 | R352: 0,00 | S352: 0,00 | T352: 0,00 | U352: 0,00 | V352: ORC2022_2 | X352: 301 | Y352: 90 | AB352: 010101
A353: =IFERROR(VLOOKUP(H353,'Contas Orç'!A:B,2,0),"N/A") -> BENEFICIOS | B353: =_xlfn.CONCAT(H353," - ",A353) -> 320103 - BENEFICIOS | C353: =DATE(YEAR(G353),MONTH(G353),1) -> 44866 | D353: =IF(K353="CREDITO",Q353,Q353*-1) -> -10771.96 | E353: 0000000122 | F353: 0006 | G353: 44886 | H353: 320103 | I353: 303 | K353: Debito | L353: RE | M353: RE - HIST CF.1933 -23010009-VR NF.413470308-HAPVID | O353: 000082 | P353: 000074 | Q353: 10771.96 | R353: 0,00 | S353: 0,00 | T353: 0,00 | U353: 0,00 | V353: ORC2022_2 | X353: 303 | Y353: 31 | AB353: 010101
A354: =IFERROR(VLOOKUP(H354,'Contas Orç'!A:B,2,0),"N/A") -> BENEFICIOS | B354: =_xlfn.CONCAT(H354," - ",A354) -> 320103 - BENEFICIOS | C354: =DATE(YEAR(G354),MONTH(G354),1) -> 44866 | D354: =IF(K354="CREDITO",Q354,Q354*-1) -> -71308.57 | E354: 0000000122 | F354: 0007 | G354: 44886 | H354: 320103 | I354: 305 | K354: Debito | L354: RE | M354: RE - HIST CF.1933 -23010009-VR NF.413470308-HAPVID | O354: 000082 | P354: 000074 | Q354: 71308.57 | R354: 0,00 | S354: 0,00 | T354: 0,00 | U354: 0,00 | V354: ORC2022_2 | X354: 305 | Y354: 90 | AB354: 010101
A355: =IFERROR(VLOOKUP(H355,'Contas Orç'!A:B,2,0),"N/A") -> BENEFICIOS | B355: =_xlfn.CONCAT(H355," - ",A355) -> 320103 - BENEFICIOS | C355: =DATE(YEAR(G355),MONTH(G355),1) -> 44866 | D355: =IF(K355="CREDITO",Q355,Q355*-1) -> -1768.58 | E355: 0000000122 | F355: 0008 | G355: 44886 | H355: 320103 | I355: 305 | K355: Debito | L355: RE | M355: RE - HIST CF.1933 -23010009-VR NF.413470308-HAPVID | O355: 000082 | P355: 000074 | Q355: 1768.58 | R355: 0,00 | S355: 0,00 | T355: 0,00 | U355: 0,00 | V355: ORC2022_2 | X355: 306 | Y355: 90 | AB355: 010101
A356: =IFERROR(VLOOKUP(H356,'Contas Orç'!A:B,2,0),"N/A") -> OUTRAS RECEITAS | B356: =_xlfn.CONCAT(H356," - ",A356) -> 310901 - OUTRAS RECEITAS | C356: =DATE(YEAR(G356),MONTH(G356),1) -> 44866 | D356: =IF(K356="CREDITO",Q356,Q356*-1) -> 10.99 | E356: 0000000123 | F356: 0001 | G356: 44895 | H356: 310901 | I356: 201 | K356: Credito | L356: RE | M356: RE - HIST TESTE PCO | O356: 000082 | P356: 000098 | Q356: 10.99 | R356: 0,00 | S356: 0,00 | T356: 0,00 | U356: 0,00 | V356: ORC2022_2 | W356: 001 | X356: 201 | AB356: 010101
A357: =IFERROR(VLOOKUP(H357,'Contas Orç'!A:B,2,0),"N/A") -> IMPOSTOS, MULTAS E TAXAS DIVERSAS | B357: =_xlfn.CONCAT(H357," - ",A357) -> 320408 - IMPOSTOS, MULTAS E TAXAS DIVERSAS | C357: =DATE(YEAR(G357),MONTH(G357),1) -> 44866 | D357: =IF(K357="CREDITO",Q357,Q357*-1) -> 10.99 | E357: 0000000123 | F357: 0002 | G357: 44895 | H357: 320408 | I357: 201 | J357: 90 | K357: Credito | L357: RE | M357: RE - HIST TESTE PCO | O357: 000082 | P357: 000098 | Q357: 10.99 | R357: 0,00 | S357: 0,00 | T357: 0,00 | U357: 0,00 | V357: ORC2022_2 | W357: 001 | X357: 201 | Y357: 90 | Z357: 201 | AB357: 010101
A358: =IFERROR(VLOOKUP(H358,'Contas Orç'!A:B,2,0),"N/A") -> IMPOSTOS, MULTAS E TAXAS DIVERSAS | B358: =_xlfn.CONCAT(H358," - ",A358) -> 320408 - IMPOSTOS, MULTAS E TAXAS DIVERSAS | C358: =DATE(YEAR(G358),MONTH(G358),1) -> 44866 | D358: =IF(K358="CREDITO",Q358,Q358*-1) -> 11.99 | E358: 0000000124 | F358: 0001 | G358: 44895 | H358: 320408 | I358: 201 | J358: 90 | K358: Credito | L358: RE | M358: RE - HIST TESTE PCO | O358: 000082 | P358: 000098 | Q358: 11.99 | R358: 0,00 | S358: 0,00 | T358: 0,00 | U358: 0,00 | V358: ORC2022_2 | W358: 001 | X358: 201 | Y358: 90 | Z358: 201 | AB358: 010101
A359: =IFERROR(VLOOKUP(H359,'Contas Orç'!A:B,2,0),"N/A") -> OUTRAS RECEITAS | B359: =_xlfn.CONCAT(H359," - ",A359) -> 310901 - OUTRAS RECEITAS | C359: =DATE(YEAR(G359),MONTH(G359),1) -> 44866 | D359: =IF(K359="CREDITO",Q359,Q359*-1) -> 11.99 | E359: 0000000124 | F359: 0002 | G359: 44895 | H359: 310901 | J359: 90 | K359: Credito | L359: RE | M359: RE - HIST TESTE PCO | O359: 000082 | P359: 000098 | Q359: 11.99 | R359: 0,00 | S359: 0,00 | T359: 0,00 | U359: 0,00 | V359: ORC2022_2 | X359: 201 | Y359: 90 | Z359: 201 | AB359: 010101
A360: =IFERROR(VLOOKUP(H360,'Contas Orç'!A:B,2,0),"N/A") -> OUTRAS RECEITAS | B360: =_xlfn.CONCAT(H360," - ",A360) -> 310901 - OUTRAS RECEITAS | C360: =DATE(YEAR(G360),MONTH(G360),1) -> 44866 | D360: =IF(K360="CREDITO",Q360,Q360*-1) -> 12.99 | E360: 0000000125 | F360: 0001 | G360: 44895 | H360: 310901 | I360: 201 | J360: 90 | K360: Credito | L360: RE | M360: RE - HIST TESTE PCO | O360: 000082 | P360: 000098 | Q360: 12.99 | R360: 0,00 | S360: 0,00 | T360: 0,00 | U360: 0,00 | V360: ORC2022_2 | X360: 201 | Y360: 90 | AB360: 010101
A361: =IFERROR(VLOOKUP(H361,'Contas Orç'!A:B,2,0),"N/A") -> IMPOSTOS, MULTAS E TAXAS DIVERSAS | B361: =_xlfn.CONCAT(H361," - ",A361) -> 320408 - IMPOSTOS, MULTAS E TAXAS DIVERSAS | C361: =DATE(YEAR(G361),MONTH(G361),1) -> 44866 | D361: =IF(K361="CREDITO",Q361,Q361*-1) -> 12.99 | E361: 0000000125 | F361: 0002 | G361: 44895 | H361: 320408 | I361: 201 | J361: 90 | K361: Credito | L361: RE | M361: RE - HIST TESTE PCO | O361: 000082 | P361: 000098 | Q361: 12.99 | R361: 0,00 | S361: 0,00 | T361: 0,00 | U361: 0,00 | V361: ORC2022_2 | X361: 201 | Y361: 90 | AB361: 010101
A362: =IFERROR(VLOOKUP(H362,'Contas Orç'!A:B,2,0),"N/A") -> IMPOSTOS, MULTAS E TAXAS DIVERSAS | B362: =_xlfn.CONCAT(H362," - ",A362) -> 320408 - IMPOSTOS, MULTAS E TAXAS DIVERSAS | C362: =DATE(YEAR(G362),MONTH(G362),1) -> 44866 | D362: =IF(K362="CREDITO",Q362,Q362*-1) -> 13.99 | E362: 0000000126 | F362: 0001 | G362: 44895 | H362: 320408 | I362: 201 | J362: 90 | K362: Credito | L362: RE | M362: RE - HIST TESTE PCO | O362: 000082 | P362: 000098 | Q362: 13.99 | R362: 0,00 | S362: 0,00 | T362: 0,00 | U362: 0,00 | V362: ORC2022_2 | X362: 201 | Y362: 90 | AB362: 010101
A363: =IFERROR(VLOOKUP(H363,'Contas Orç'!A:B,2,0),"N/A") -> OUTRAS RECEITAS | B363: =_xlfn.CONCAT(H363," - ",A363) -> 310901 - OUTRAS RECEITAS | C363: =DATE(YEAR(G363),MONTH(G363),1) -> 44866 | D363: =IF(K363="CREDITO",Q363,Q363*-1) -> 13.99 | E363: 0000000126 | F363: 0002 | G363: 44895 | H363: 310901 | I363: 201 | J363: 90 | K363: Credito | L363: RE | M363: RE - HIST TESTE PCO | O363: 000082 | P363: 000098 | Q363: 13.99 | R363: 0,00 | S363: 0,00 | T363: 0,00 | U363: 0,00 | V363: ORC2022_2 | W363: 001 | X363: 201 | Y363: 90 | AB363: 010101
A364: =IFERROR(VLOOKUP(H364,'Contas Orç'!A:B,2,0),"N/A") -> DESPESAS FINANCEIRAS | B364: =_xlfn.CONCAT(H364," - ",A364) -> 380201 - DESPESAS FINANCEIRAS | C364: =DATE(YEAR(G364),MONTH(G364),1) -> 44866 | D364: =IF(K364="CREDITO",Q364,Q364*-1) -> 2.99 | E364: 0000000126 | F364: 0003 | G364: 44895 | H364: 380201 | I364: 201 | J364: 90 | K364: Credito | L364: RE | M364: RE - HIST TESTE PCO | O364: 000082 | P364: 000098 | Q364: 2.99 | R364: 0,00 | S364: 0,00 | T364: 0,00 | U364: 0,00 | V364: ORC2022_2 | W364: 001 | X364: 201 | Y364: 90 | AB364: 010101
A365: =IFERROR(VLOOKUP(H365,'Contas Orç'!A:B,2,0),"N/A") -> OUTRAS RECEITAS | B365: =_xlfn.CONCAT(H365," - ",A365) -> 310901 - OUTRAS RECEITAS | C365: =DATE(YEAR(G365),MONTH(G365),1) -> 44866 | D365: =IF(K365="CREDITO",Q365,Q365*-1) -> 2.99 | E365: 0000000126 | F365: 0004 | G365: 44895 | H365: 310901 | I365: 201 | J365: 90 | K365: Credito | L365: RE | M365: RE - HIST TESTE PCO | O365: 000082 | P365: 000098 | Q365: 2.99 | R365: 0,00 | S365: 0,00 | T365: 0,00 | U365: 0,00 | V365: ORC2022_2 | W365: 001 | X365: 201 | Y365: 90 | AB365: 010101
A366: =IFERROR(VLOOKUP(H366,'Contas Orç'!A:B,2,0),"N/A") -> RECEITA BRUTA DE TRANSPORTES | B366: =_xlfn.CONCAT(H366," - ",A366) -> 310101 - RECEITA BRUTA DE TRANSPORTES | C366: =DATE(YEAR(G366),MONTH(G366),1) -> 44562 | D366: =IF(K366="CREDITO",Q366,Q366*-1) -> 595449.98 | E366: 0000000127 | F366: 0001 | G366: 44562 | H366: 310101 | I366: 304 | J366: 11 | K366: Credito | L366: 0R | M366: FORECAST: ORC2022_2 - ORCAMENTO 2022 | VERSAO: 0012 | O366: 000252 | P366: 000132 | Q366: 595449.98 | R366: 0,00 | S366: 0,00 | T366: 0,00 | U366: 0,00 | V366: ORC2022_2 | W366: 0012
A367: =IFERROR(VLOOKUP(H367,'Contas Orç'!A:B,2,0),"N/A") -> RECEITA BRUTA DE TRANSPORTES | B367: =_xlfn.CONCAT(H367," - ",A367) -> 310101 - RECEITA BRUTA DE TRANSPORTES | C367: =DATE(YEAR(G367),MONTH(G367),1) -> 44593 | D367: =IF(K367="CREDITO",Q367,Q367*-1) -> 668030.77 | E367: 0000000127 | F367: 0002 | G367: 44593 | H367: 310101 | I367: 304 | J367: 11 | K367: Credito | L367: 0R | M367: FORECAST: ORC2022_2 - ORCAMENTO 2022 | VERSAO: 0012 | O367: 000252 | P367: 000132 | Q367: 668030.77 | R367: 0,00 | S367: 0,00 | T367: 0,00 | U367: 0,00 | V367: ORC2022_2 | W367: 0012
A368: =IFERROR(VLOOKUP(H368,'Contas Orç'!A:B,2,0),"N/A") -> RECEITA BRUTA DE TRANSPORTES | B368: =_xlfn.CONCAT(H368," - ",A368) -> 310101 - RECEITA BRUTA DE TRANSPORTES | C368: =DATE(YEAR(G368),MONTH(G368),1) -> 44621 | D368: =IF(K368="CREDITO",Q368,Q368*-1) -> 800240.31 | E368: 0000000127 | F368: 0003 | G368: 44621 | H368: 310101 | I368: 304 | J368: 11 | K368: Credito | L368: 0R | M368: FORECAST: ORC2022_2 - ORCAMENTO 2022 | VERSAO: 0012 | O368: 000252 | P368: 000132 | Q368: 800240.31 | R368: 0,00 | S368: 0,00 | T368: 0,00 | U368: 0,00 | V368: ORC2022_2 | W368: 0012
A369: =IFERROR(VLOOKUP(H369,'Contas Orç'!A:B,2,0),"N/A") -> RECEITA BRUTA DE TRANSPORTES | B369: =_xlfn.CONCAT(H369," - ",A369) -> 310101 - RECEITA BRUTA DE TRANSPORTES | C369: =DATE(YEAR(G369),MONTH(G369),1) -> 44652 | D369: =IF(K369="CREDITO",Q369,Q369*-1) -> 817913.21 | E369: 0000000127 | F369: 0004 | G369: 44652 | H369: 310101 | I369: 304 | J369: 11 | K369: Credito | L369: 0R | M369: FORECAST: ORC2022_2 - ORCAMENTO 2022 | VERSAO: 0012 | O369: 000252 | P369: 000132 | Q369: 817913.21 | R369: 0,00 | S369: 0,00 | T369: 0,00 | U369: 0,00 | V369: ORC2022_2 | W369: 0012
A370: =IFERROR(VLOOKUP(H370,'Contas Orç'!A:B,2,0),"N/A") -> RECEITA BRUTA DE TRANSPORTES | B370: =_xlfn.CONCAT(H370," - ",A370) -> 310101 - RECEITA BRUTA DE TRANSPORTES | C370: =DATE(YEAR(G370),MONTH(G370),1) -> 44682 | D370: =IF(K370="CREDITO",Q370,Q370*-1) -> 1165336.9 | E370: 0000000127 | F370: 0005 | G370: 44682 | H370: 310101 | I370: 304 | J370: 11 | K370: Credito | L370: 0R | M370: FORECAST: ORC2022_2 - ORCAMENTO 2022 | VERSAO: 0012 | O370: 000252 | P370: 000132 | Q370: 1165336.9 | R370: 0,00 | S370: 0,00 | T370: 0,00 | U370: 0,00 | V370: ORC2022_2 | W370: 0012
A371: =IFERROR(VLOOKUP(H371,'Contas Orç'!A:B,2,0),"N/A") -> RECEITA BRUTA DE TRANSPORTES | B371: =_xlfn.CONCAT(H371," - ",A371) -> 310101 - RECEITA BRUTA DE TRANSPORTES | C371: =DATE(YEAR(G371),MONTH(G371),1) -> 44713 | D371: =IF(K371="CREDITO",Q371,Q371*-1) -> 1143668.6 | E371: 0000000127 | F371: 0006 | G371: 44713 | H371: 310101 | I371: 304 | J371: 11 | K371: Credito | L371: 0R | M371: FORECAST: ORC2022_2 - ORCAMENTO 2022 | VERSAO: 0012 | O371: 000252 | P371: 000132 | Q371: 1143668.6 | R371: 0,00 | S371: 0,00 | T371: 0,00 | U371: 0,00 | V371: ORC2022_2 | W371: 0012
A372: =IFERROR(VLOOKUP(H372,'Contas Orç'!A:B,2,0),"N/A") -> RECEITA BRUTA DE TRANSPORTES | B372: =_xlfn.CONCAT(H372," - ",A372) -> 310101 - RECEITA BRUTA DE TRANSPORTES | C372: =DATE(YEAR(G372),MONTH(G372),1) -> 44743 | D372: =IF(K372="CREDITO",Q372,Q372*-1) -> 1455589.7 | E372: 0000000127 | F372: 0007 | G372: 44743 | H372: 310101 | I372: 304 | J372: 11 | K372: Credito | L372: 0R | M372: FORECAST: ORC2022_2 - ORCAMENTO 2022 | VERSAO: 0012 | O372: 000252 | P372: 000132 | Q372: 1455589.7 | R372: 0,00 | S372: 0,00 | T372: 0,00 | U372: 0,00 | V372: ORC2022_2 | W372: 0012
A373: =IFERROR(VLOOKUP(H373,'Contas Orç'!A:B,2,0),"N/A") -> RECEITA BRUTA DE TRANSPORTES | B373: =_xlfn.CONCAT(H373," - ",A373) -> 310101 - RECEITA BRUTA DE TRANSPORTES | C373: =DATE(YEAR(G373),MONTH(G373),1) -> 44774 | D373: =IF(K373="CREDITO",Q373,Q373*-1) -> 1316310.1 | E373: 0000000127 | F373: 0008 | G373: 44774 | H373: 310101 | I373: 304 | J373: 11 | K373: Credito | L373: 0R | M373: FORECAST: ORC2022_2 - ORCAMENTO 2022 | VERSAO: 0012 | O373: 000252 | P373: 000132 | Q373: 1316310.1 | R373: 0,00 | S373: 0,00 | T373: 0,00 | U373: 0,00 | V373: ORC2022_2 | W373: 0012
A374: =IFERROR(VLOOKUP(H374,'Contas Orç'!A:B,2,0),"N/A") -> RECEITA BRUTA DE TRANSPORTES | B374: =_xlfn.CONCAT(H374," - ",A374) -> 310101 - RECEITA BRUTA DE TRANSPORTES | C374: =DATE(YEAR(G374),MONTH(G374),1) -> 44805 | D374: =IF(K374="CREDITO",Q374,Q374*-1) -> 1516365.9 | E374: 0000000127 | F374: 0009 | G374: 44805 | H374: 310101 | I374: 304 | J374: 11 | K374: Credito | L374: 0R | M374: FORECAST: ORC2022_2 - ORCAMENTO 2022 | VERSAO: 0012 | O374: 000252 | P374: 000132 | Q374: 1516365.9 | R374: 0,00 | S374: 0,00 | T374: 0,00 | U374: 0,00 | V374: ORC2022_2 | W374: 0012
A375: =IFERROR(VLOOKUP(H375,'Contas Orç'!A:B,2,0),"N/A") -> RECEITA BRUTA DE TRANSPORTES | B375: =_xlfn.CONCAT(H375," - ",A375) -> 310101 - RECEITA BRUTA DE TRANSPORTES | C375: =DATE(YEAR(G375),MONTH(G375),1) -> 44805 | D375: =IF(K375="CREDITO",Q375,Q375*-1) -> 3873.69 | E375: 0000000127 | F375: 0010 | G375: 44805 | H375: 310101 | I375: 305 | J375: 21 | K375: Credito | L375: 0R | M375: FORECAST: ORC2022_2 - ORCAMENTO 2022 | VERSAO: 0012 | O375: 000252 | P375: 000132 | Q375: 3873.69 | R375: 0,00 | S375: 0,00 | T375: 0,00 | U375: 0,00 | V375: ORC2022_2 | W375: 0012
A376: =IFERROR(VLOOKUP(H376,'Contas Orç'!A:B,2,0),"N/A") -> RECEITA BRUTA DE TRANSPORTES | B376: =_xlfn.CONCAT(H376," - ",A376) -> 310101 - RECEITA BRUTA DE TRANSPORTES | C376: =DATE(YEAR(G376),MONTH(G376),1) -> 44835 | D376: =IF(K376="CREDITO",Q376,Q376*-1) -> 1531529.6 | E376: 0000000127 | F376: 0011 | G376: 44835 | H376: 310101 | I376: 304 | J376: 11 | K376: Credito | L376: 0R | M376: FORECAST: ORC2022_2 - ORCAMENTO 2022 | VERSAO: 0012 | O376: 000252 | P376: 000132 | Q376: 1531529.6 | R376: 0,00 | S376: 0,00 | T376: 0,00 | U376: 0,00 | V376: ORC2022_2 | W376: 0012
A377: =IFERROR(VLOOKUP(H377,'Contas Orç'!A:B,2,0),"N/A") -> RECEITA BRUTA DE TRANSPORTES | B377: =_xlfn.CONCAT(H377," - ",A377) -> 310101 - RECEITA BRUTA DE TRANSPORTES | C377: =DATE(YEAR(G377),MONTH(G377),1) -> 44835 | D377: =IF(K377="CREDITO",Q377,Q377*-1) -> 3912.43 | E377: 0000000127 | F377: 0012 | G377: 44835 | H377: 310101 | I377: 305 | J377: 21 | K377: Credito | L377: 0R | M377: FORECAST: ORC2022_2 - ORCAMENTO 2022 | VERSAO: 0012 | O377: 000252 | P377: 000132 | Q377: 3912.43 | R377: 0,00 | S377: 0,00 | T377: 0,00 | U377: 0,00 | V377: ORC2022_2 | W377: 0012
... A3853: =IFERROR(VLOOKUP(H3853,'Contas Orç'!A:B,2,0),"N/A") -> CONTRIBUICAO SOCIAL | B3853: =_xlfn.CONCAT(H3853," - ",A3853) -> 910101002 - CONTRIBUICAO SOCIAL | C3853: =DATE(YEAR(G3853),MONTH(G3853),1) -> 44896 | D3853: =IF(K3853="CREDITO",Q3853,Q3853*-1) -> 865851.65 | E3853: 0000000127 | F3853: 3488 | G3853: 44896 | H3853: 910101002 | I3853: 201 | J3853: 90 | K3853: Credito | L3853: 0R | M3853: FORECAST: ORC2022_2 - ORCAMENTO 2022 | VERSAO: 0012 | O3853: 000252 | P3853: 000132 | Q3853: 865851.65 | R3853: 0,00 | S3853: 0,00 | T3853: 0,00 | U3853: 0,00 | V3853: ORC2022_2 | W3853: 0012
A3854: =IFERROR(VLOOKUP(H3854,'Contas Orç'!A:B,2,0),"N/A") -> RECEITA BRUTA DE TRANSPORTES | B3854: =_xlfn.CONCAT(H3854," - ",A3854) -> 310101 - RECEITA BRUTA DE TRANSPORTES | C3854: =DATE(YEAR(G3854),MONTH(G3854),1) -> 44896 | D3854: =IF(K3854="CREDITO",Q3854,Q3854*-1) -> 10950 | E3854: 0000000128 | F3854: 0001 | G3854: 44901 | H3854: 310101 | I3854: 304 | J3854: 11 | K3854: Credito | L3854: RE | M3854: RE - NF (000053720) P: (21010001) C: (HAPAG LLOYD AG) | O3854: 000101 | P3854: 000032 | Q3854: 10950 | R3854: 0,00 | S3854: 0,00 | T3854: 0,00 | U3854: 0,00 | V3854: ORC2022_2 | W3854: 001 | X3854: 304 | Y3854: 11 | AB3854: 010101
A3855: =IFERROR(VLOOKUP(H3855,'Contas Orç'!A:B,2,0),"N/A") -> RECEITA BRUTA DE TRANSPORTES | B3855: =_xlfn.CONCAT(H3855," - ",A3855) -> 310101 - RECEITA BRUTA DE TRANSPORTES | C3855: =DATE(YEAR(G3855),MONTH(G3855),1) -> 44896 | D3855: =IF(K3855="CREDITO",Q3855,Q3855*-1) -> 6417.67 | E3855: 0000000129 | F3855: 0001 | G3855: 44903 | H3855: 310101 | I3855: 304 | J3855: 11 | K3855: Credito | L3855: RE | M3855: RE - NF (000053722) P: (21010001) C: (PGL PRIME AGENCIAMENTO | O3855: 000101 | P3855: 000032 | Q3855: 6417.67 | R3855: 0,00 | S3855: 0,00 | T3855: 0,00 | U3855: 0,00 | V3855: ORC2022_2 | W3855: 001 | X3855: 304 | Y3855: 11 | AB3855: 010101
A3856: =IFERROR(VLOOKUP(H3856,'Contas Orç'!A:B,2,0),"N/A") -> RECEITA BRUTA DE TRANSPORTES | B3856: =_xlfn.CONCAT(H3856," - ",A3856) -> 310101 - RECEITA BRUTA DE TRANSPORTES | C3856: =DATE(YEAR(G3856),MONTH(G3856),1) -> 44896 | D3856: =IF(K3856="CREDITO",Q3856,Q3856*-1) -> 46608.9 | E3856: 0000000130 | F3856: 0001 | G3856: 44907 | H3856: 310101 | I3856: 304 | J3856: 11 | K3856: Credito | L3856: RE | M3856: RE - NF (000053723) P: (21010001) C: (ACO VERDE DO BRASIL S. | O3856: 000101 | P3856: 000032 | Q3856: 46608.9 | R3856: 0,00 | S3856: 0,00 | T3856: 0,00 | U3856: 0,00 | V3856: ORC2022_2 | W3856: 001 | X3856: 304 | Y3856: 11 | AB3856: 010101
A3857: =IFERROR(VLOOKUP(H3857,'Contas Orç'!A:B,2,0),"N/A") -> RECEITA BRUTA DE TRANSPORTES | B3857: =_xlfn.CONCAT(H3857," - ",A3857) -> 310101 - RECEITA BRUTA DE TRANSPORTES | C3857: =DATE(YEAR(G3857),MONTH(G3857),1) -> 44896 | D3857: =IF(K3857="CREDITO",Q3857,Q3857*-1) -> 1499.19 | E3857: 0000000131 | F3857: 0001 | G3857: 44907 | H3857: 310101 | I3857: 304 | J3857: 11 | K3857: Credito | L3857: RE | M3857: RE - NF (000053724) P: (21010001) C: (ALIANCA NAVEGACAO E LO | O3857: 000101 | P3857: 000032 | Q3857: 1499.19 | R3857: 0,00 | S3857: 0,00 | T3857: 0,00 | U3857: 0,00 | V3857: ORC2022_2 | W3857: 001 | X3857: 304 | Y3857: 11 | AB3857: 010101
A3858: =IFERROR(VLOOKUP(H3858,'Contas Orç'!A:B,2,0),"N/A") -> RECEITA BRUTA DE TRANSPORTES | B3858: =_xlfn.CONCAT(H3858," - ",A3858) -> 310101 - RECEITA BRUTA DE TRANSPORTES | C3858: =DATE(YEAR(G3858),MONTH(G3858),1) -> 44896 | D3858: =IF(K3858="CREDITO",Q3858,Q3858*-1) -> 1549.49 | E3858: 0000000132 | F3858: 0001 | G3858: 44907 | H3858: 310101 | I3858: 304 | J3858: 11 | K3858: Credito | L3858: RE | M3858: RE - NF (000053725) P: (21010001) C: (MERCOSUL LINE NAVEGACA | O3858: 000101 | P3858: 000032 | Q3858: 1549.49 | R3858: 0,00 | S3858: 0,00 | T3858: 0,00 | U3858: 0,00 | V3858: ORC2022_2 | W3858: 001 | X3858: 304 | Y3858: 11 | AB3858: 010101
A3859: =IFERROR(VLOOKUP(H3859,'Contas Orç'!A:B,2,0),"N/A") -> RECEITA BRUTA DE TRANSPORTES | B3859: =_xlfn.CONCAT(H3859," - ",A3859) -> 310101 - RECEITA BRUTA DE TRANSPORTES | C3859: =DATE(YEAR(G3859),MONTH(G3859),1) -> 44896 | D3859: =IF(K3859="CREDITO",Q3859,Q3859*-1) -> 578.61 | E3859: 0000000133 | F3859: 0001 | G3859: 44907 | H3859: 310101 | I3859: 304 | J3859: 11 | K3859: Credito | L3859: RE | M3859: RE - NF (000053726) P: (21010001) C: (MERCOSUL LINE NAVEGACA | O3859: 000101 | P3859: 000032 | Q3859: 578.61 | R3859: 0,00 | S3859: 0,00 | T3859: 0,00 | U3859: 0,00 | V3859: ORC2022_2 | W3859: 001 | X3859: 304 | Y3859: 11 | AB3859: 010101
A3860: =IFERROR(VLOOKUP(H3860,'Contas Orç'!A:B,2,0),"N/A") -> RECEITA BRUTA DE TRANSPORTES | B3860: =_xlfn.CONCAT(H3860," - ",A3860) -> 310101 - RECEITA BRUTA DE TRANSPORTES | C3860: =DATE(YEAR(G3860),MONTH(G3860),1) -> 44896 | D3860: =IF(K3860="CREDITO",Q3860,Q3860*-1) -> 10950 | E3860: 0000000134 | F3860: 0001 | G3860: 44908 | H3860: 310101 | I3860: 304 | J3860: 11 | K3860: Credito | L3860: RE | M3860: RE - NF (000053728) P: (21010001) C: (HAPAG LLOYD AG) | O3860: 000101 | P3860: 000032 | Q3860: 10950 | R3860: 0,00 | S3860: 0,00 | T3860: 0,00 | U3860: 0,00 | V3860: ORC2022_2 | W3860: 001 | X3860: 304 | Y3860: 11 | AB3860: 010101
A3861: =IFERROR(VLOOKUP(H3861,'Contas Orç'!A:B,2,0),"N/A") -> RECEITA BRUTA DE TRANSPORTES | B3861: =_xlfn.CONCAT(H3861," - ",A3861) -> 310101 - RECEITA BRUTA DE TRANSPORTES | C3861: =DATE(YEAR(G3861),MONTH(G3861),1) -> 44896 | D3861: =IF(K3861="CREDITO",Q3861,Q3861*-1) -> 1593.11 | E3861: 0000000135 | F3861: 0001 | G3861: 44909 | H3861: 310101 | I3861: 304 | J3861: 11 | K3861: Credito | L3861: RE | M3861: RE - NF (000053729) P: (21010001) C: (VESTAS DO BRASIL ENERG | O3861: 000101 | P3861: 000046 | Q3861: 1593.11 | R3861: 0,00 | S3861: 0,00 | T3861: 0,00 | U3861: 0,00 | V3861: ORC2022_2 | W3861: 001 | X3861: 304 | Y3861: 11 | AB3861: 010101
A3862: =IFERROR(VLOOKUP(H3862,'Contas Orç'!A:B,2,0),"N/A") -> RECEITA BRUTA DE TRANSPORTES | B3862: =_xlfn.CONCAT(H3862," - ",A3862) -> 310101 - RECEITA BRUTA DE TRANSPORTES | C3862: =DATE(YEAR(G3862),MONTH(G3862),1) -> 44896 | D3862: =IF(K3862="CREDITO",Q3862,Q3862*-1) -> 410.21 | E3862: 0000000136 | F3862: 0001 | G3862: 44909 | H3862: 310101 | I3862: 304 | J3862: 11 | K3862: Credito | L3862: RE | M3862: RE - NF (000053730) P: (21010001) C: (VESTAS DO BRASIL ENERG | O3862: 000101 | P3862: 000046 | Q3862: 410.21 | R3862: 0,00 | S3862: 0,00 | T3862: 0,00 | U3862: 0,00 | V3862: ORC2022_2 | W3862: 001 | X3862: 304 | Y3862: 11 | AB3862: 010101
...

Sheet Base_24.11
A1: Desc_Conta | B1: VERIFICAÇÃO | C1: Lote | D1: Item | E1: Data | F1: C.O. | G1: Classe | H1: Operacao | I1: Tipo | J1: Tp. Saldo | K1: Historico | L1: Unid. Medida | M1: Processo | N1: Usuario | O1: Vlr.Lancto. | P1: Vlr.2a Moeda | Q1: Vlr.3a Moeda | R1: Vlr.4a Moeda | S1: Vlr.5a Moeda | T1: Cod.Planilha | U1: Versao | V1: Centro Custo | W1: It.Contabil | X1: Classe Valor | Y1: Lc.Bloqueio? | Z1: Und. Orc.
A2: =VLOOKUP(F2,'Contas Orç'!A:B,2,0) -> PECAS E ACESSORIOS | B2: =VLOOKUP(C2,Base_20.12!E:E,1,0) -> 0000000001 | C2: 0000000001 | D2: 0001 | E2: 44874 | F2: 320301004 | G2: 304 | H2: 11 | I2: Credito | J2: EM | K2: EM - PEDIDO (013491) ITEM +(0001) / (ITERRUPTOR DO NEUTRO - | M2: 000052 | N2: 000132 | O2: 25,00 | P2: 0,00 | Q2: 0,00 | R2: 0,00 | S2: 0,00 | T2: ORC2022 | V2: 304 | W2: 11 | Z2: 010101
A3: =VLOOKUP(F3,'Contas Orç'!A:B,2,0) -> PECAS E ACESSORIOS | B3: =VLOOKUP(C3,Base_20.12!E:E,1,0) -> 0000000001 | C3: 0000000001 | D3: 0002 | E3: 44874 | F3: 330301004 | G3: 201 | H3: 11 | I3: Credito | J3: EM | K3: EM - PEDIDO (013491) ITEM +(0002) / (MANCAL PARA LOCK (GUIA | M3: 000052 | N3: 000132 | O3: 25,00 | P3: 0,00 | Q3: 0,00 | R3: 0,00 | S3: 0,00 | T3: ORC2022 | V3: 201 | W3: 11 | Z3: 010101
A4: =VLOOKUP(F4,'Contas Orç'!A:B,2,0) -> PECAS E ACESSORIOS | B4: =VLOOKUP(C4,Base_20.12!E:E,1,0) -> 0000000002 | C4: 0000000002 | D4: 0001 | E4: 44874 | F4: 320301004 | G4: 304 | H4: 11 | I4: Credito | J4: RE | K4: RE - NF (909090909) P: (11150482 ) F: (000003) | M4: 000054 | N4: 000132 | O4: 25,00 | P4: 0,00 | Q4: 0,00 | R4: 0,00 | S4: 0,00 | V4: 304 | W4: 11 | Z4: 010101
A5: =VLOOKUP(F5,'Contas Orç'!A:B,2,0) -> PECAS E ACESSORIOS | B5: =VLOOKUP(C5,Base_20.12!E:E,1,0) -> 0000000002 | C5: 0000000002 | D5: 0002 | E5: 44874 | F5: 320301004 | G5: 304 | H5: 11 | I5: Debito | J5: EM | K5: EM - NF (909090909) P: (11150482 ) F: (000003) | M5: 000054 | N5: 000132 | O5: 25,00 | P5: 0,00 | Q5: 0,00 | R5: 0,00 | S5: 0,00 | V5: 304 | W5: 11 | Z5: 010101
A6: =VLOOKUP(F6,'Contas Orç'!A:B,2,0) -> PECAS E ACESSORIOS | B6: =VLOOKUP(C6,Base_20.12!E:E,1,0) -> 0000000002 | C6: 0000000002 | D6: 0003 | E6: 44874 | F6: 330301004 | G6: 201 | H6: 11 | I6: Credito | J6: RE | K6: RE - NF (909090909) P: (11010003 ) F: (000003) | M6: 000054 | N6: 000132 | O6: 25,00 | P6: 0,00 | Q6: 0,00 | R6: 0,00 | S6: 0,00 | V6: 201 | W6: 11 | Z6: 010101
A7: =VLOOKUP(F7,'Contas Orç'!A:B,2,0) -> PECAS E ACESSORIOS | B7: =VLOOKUP(C7,Base_20.12!E:E,1,0) -> 0000000002 | C7: 0000000002 | D7: 0004 | E7: 44874 | F7: 330301004 | G7: 201 | H7: 11 | I7: Debito | J7: EM | K7: EM - NF (909090909) P: (11010003 ) F: (000003) | M7: 000054 | N7: 000132 | O7: 25,00 | P7: 0,00 | Q7: 0,00 | R7: 0,00 | S7: 0,00 | V7: 201 | W7: 11 | Z7: 010101
A8: =VLOOKUP(F8,'Contas Orç'!A:B,2,0) -> PECAS E ACESSORIOS | B8: =VLOOKUP(C8,Base_20.12!E:E,1,0) -> 0000000003 | C8: 0000000003 | D8: 0001 | E8: 44876 | F8: 320301004 | G8: 301 | H8: 90 | I8: Credito | J8: EM | K8: EM - PEDIDO (000146) | (11280021 ) | F: (000361/0001) | M8: 000055 | N8: 000132 | O8: 345,00 | P8: 0,00 | Q8: 0,00 | R8: 0,00 | S8: 0,00 | T8: ORC2022 | W8: 90 | Z8: 010101
A9: =VLOOKUP(F9,'Contas Orç'!A:B,2,0) -> #N/A | B9: =VLOOKUP(C9,Base_20.12!E:E,1,0) -> 0000000004 | C9: 0000000004 | D9: 0001 | E9: 44879 | G9: 305 | H9: 21 | I9: Credito | J9: EM | K9: EM - PEDIDO (011661) ITEM +(0001) / (EMPILHADEIRA HYSTER H50 | M9: 000055 | N9: 000044 | O9: 170.000,00 | P9: 0,00 | Q9: 0,00 | R9: 0,00 | S9: 0,00 | V9: 305 | W9: 21 | Z9: 010101
A10: =VLOOKUP(F10,'Contas Orç'!A:B,2,0) -> #N/A | B10: =VLOOKUP(C10,Base_20.12!E:E,1,0) -> 0000000004 | C10: 0000000004 | D10: 0002 | E10: 44879 | G10: 305 | H10: 21 | I10: Credito | J10: EM | K10: EM - PEDIDO (011661) ITEM +(0002) / (EMPILHADEIRA HYSTER H50 | M10: 000055 | N10: 000044 | O10: 172.000,00 | P10: 0,00 | Q10: 0,00 | R10: 0,00 | S10: 0,00 | V10: 305 | W10: 21 | Z10: 010101
A11: =VLOOKUP(F11,'Contas Orç'!A:B,2,0) -> PJ-OUTROS SERVICOS CONTRATADOS-PJ | B11: =VLOOKUP(C11,Base_20.12!E:E,1,0) -> 0000000005 | C11: 0000000005 | D11: 0001 | E11: 44879 | F11: 330201006 | G11: 211 | H11: 51 | I11: Credito | J11: EM | K11: EM - PEDIDO (013494) ITEM +(0001) / (SERVICO DE EMPREITADA / | M11: 000055 | N11: 000000 | O11: 33.809,00 | P11: 0,00 | Q11: 0,00 | R11: 0,00 | S11: 0,00 | V11: 211 | W11: 51 | Z11: 010101
A12: =VLOOKUP(F12,'Contas Orç'!A:B,2,0) -> BENEFICIOS | B12: =VLOOKUP(C12,Base_20.12!E:E,1,0) -> 0000000007 | C12: 0000000007 | D12: 0001 | E12: 44879 | F12: 330103 | G12: 207 | H12: 90 | I12: Credito | J12: EM | K12: EM - PEDIDO (013492) ITEM +(0001) / (ASSISTENCIA MEDICA | M12: 000055 | N12: 000000 | O12: 655,00 | P12: 0,00 | Q12: 0,00 | R12: 0,00 | S12: 0,00 | V12: 207 | W12: 90 | Z12: 010101
A13: =VLOOKUP(F13,'Contas Orç'!A:B,2,0) -> BENEFICIOS | B13: =VLOOKUP(C13,Base_20.12!E:E,1,0) -> 0000000007 | C13: 0000000007 | D13: 0002 | E13: 44879 | F13: 330103 | G13: 208 | H13: 90 | I13: Credito | J13: EM | K13: EM - PEDIDO (013492) ITEM +(0002) / (ASSISTENCIA MEDICA | M13: 000055 | N13: 000000 | O13: 1.267,00 | P13: 0,00 | Q13: 0,00 | R13: 0,00 | S13: 0,00 | V13: 208 | W13: 90 | Z13: 010101
A14: =VLOOKUP(F14,'Contas Orç'!A:B,2,0) -> BENEFICIOS | B14: =VLOOKUP(C14,Base_20.12!E:E,1,0) -> 0000000007 | C14: 0000000007 | D14: 0003 | E14: 44879 | F14: 330103 | G14: 209 | H14: 90 | I14: Credito | J14: EM | K14: EM - PEDIDO (013492) ITEM +(0003) / (ASSISTENCIA MEDICA | M14: 000055 | N14: 000000 | O14: 516,00 | P14: 0,00 | Q14: 0,00 | R14: 0,00 | S14: 0,00 | V14: 209 | W14: 90 | Z14: 010101
A15: =VLOOKUP(F15,'Contas Orç'!A:B,2,0) -> BENEFICIOS | B15: =VLOOKUP(C15,Base_20.12!E:E,1,0) -> 0000000007 | C15: 0000000007 | D15: 0004 | E15: 44879 | F15: 320103 | G15: 301 | H15: 11 | I15: Credito | J15: EM | K15: EM - PEDIDO (013492) ITEM +(0004) / (ASSISTENCIA MEDICA | M15: 000055 | N15: 000000 | O15: 3.874,00 | P15: 0,00 | Q15: 0,00 | R15: 0,00 | S15: 0,00 | V15: 301 | W15: 11 | Z15: 010101
A16: =VLOOKUP(F16,'Contas Orç'!A:B,2,0) -> BENEFICIOS | B16: =VLOOKUP(C16,Base_20.12!E:E,1,0) -> 0000000007 | C16: 0000000007 | D16: 0005 | E16: 44879 | F16: 320103 | G16: 302 | H16: 11 | I16: Credito | J16: EM | K16: EM - PEDIDO (013492) ITEM +(0005) / (ASSISTENCIA MEDICA | M16: 000055 | N16: 000000 | O16: 4.905,00 | P16: 0,00 | Q16: 0,00 | R16: 0,00 | S16: 0,00 | V16: 302 | W16: 11 | Z16: 010101
A17: =VLOOKUP(F17,'Contas Orç'!A:B,2,0) -> BENEFICIOS | B17: =VLOOKUP(C17,Base_20.12!E:E,1,0) -> 0000000007 | C17: 0000000007 | D17: 0006 | E17: 44879 | F17: 320103 | G17: 304 | H17: 21 | I17: Credito | J17: EM | K17: EM - PEDIDO (013492) ITEM +(0006) / (ASSISTENCIA MEDICA | M17: 000055 | N17: 000000 | O17: 11.568,00 | P17: 0,00 | Q17: 0,00 | R17: 0,00 | S17: 0,00 | V17: 304 | W17: 21 | Z17: 010101
A18: =VLOOKUP(F18,'Contas Orç'!A:B,2,0) -> BENEFICIOS | B18: =VLOOKUP(C18,Base_20.12!E:E,1,0) -> 0000000007 | C18: 0000000007 | D18: 0007 | E18: 44879 | F18: 320103 | G18: 305 | H18: 33 | I18: Credito | J18: EM | K18: EM - PEDIDO (013492) ITEM +(0007) / (ASSISTENCIA MEDICA | M18: 000055 | N18: 000000 | O18: 608,00 | P18: 0,00 | Q18: 0,00 | R18: 0,00 | S18: 0,00 | V18: 305 | W18: 33 | Z18: 010101
A19: =VLOOKUP(F19,'Contas Orç'!A:B,2,0) -> BENEFICIOS | B19: =VLOOKUP(C19,Base_20.12!E:E,1,0) -> 0000000007 | C19: 0000000007 | D19: 0008 | E19: 44879 | F19: 330103 | G19: 206 | H19: 90 | I19: Credito | J19: EM | K19: EM - PEDIDO (013492) ITEM +(0008) / (ASSISTENCIA MEDICA | M19: 000055 | N19: 000000 | O19: 563,00 | P19: 0,00 | Q19: 0,00 | R19: 0,00 | S19: 0,00 | V19: 206 | W19: 90 | Z19: 010101
A20: =VLOOKUP(F20,'Contas Orç'!A:B,2,0) -> BENEFICIOS | B20: =VLOOKUP(C20,Base_20.12!E:E,1,0) -> 0000000007 | C20: 0000000007 | D20: 0009 | E20: 44879 | F20: 320103 | G20: 301 | H20: 90 | I20: Credito | J20: EM | K20: EM - PEDIDO (013492) ITEM +(0009) / (ASSISTENCIA MEDICA | M20: 000055 | N20: 000000 | O20: 704,00 | P20: 0,00 | Q20: 0,00 | R20: 0,00 | S20: 0,00 | V20: 301 | W20: 90 | Z20: 010101
A21: =VLOOKUP(F21,'Contas Orç'!A:B,2,0) -> BENEFICIOS | B21: =VLOOKUP(C21,Base_20.12!E:E,1,0) -> 0000000007 | C21: 0000000007 | D21: 0010 | E21: 44879 | F21: 320103 | G21: 303 | H21: 31 | I21: Credito | J21: EM | K21: EM - PEDIDO (013492) ITEM +(0010) / (ASSISTENCIA MEDICA | M21: 000055 | N21: 000000 | O21: 11.421,00 | P21: 0,00 | Q21: 0,00 | R21: 0,00 | S21: 0,00 | V21: 303 | W21: 31 | Z21: 010101
A22: =VLOOKUP(F22,'Contas Orç'!A:B,2,0) -> BENEFICIOS | B22: =VLOOKUP(C22,Base_20.12!E:E,1,0) -> 0000000007 | C22: 0000000007 | D22: 0011 | E22: 44879 | F22: 320103 | G22: 305 | H22: 90 | I22: Credito | J22: EM | K22: EM - PEDIDO (013492) ITEM +(0011) / (ASSISTENCIA MEDICA | M22: 000055 | N22: 000000 | O22: 71.588,00 | P22: 0,00 | Q22: 0,00 | R22: 0,00 | S22: 0,00 | V22: 305 | W22: 90 | Z22: 010101
... A114: =VLOOKUP(F114,'Contas Orç'!A:B,2,0) -> PJ-OUTROS SERVICOS CONTRATADOS-PJ | B114: =VLOOKUP(C114,Base_20.12!E:E,1,0) -> 0000000025 | C114: 0000000025 | D114: 0002 | E114: 44879 | F114: 330201006 | G114: 211 | H114: 51 | I114: Debito | J114: EM | K114: EM - PED (013494) PROD: (23010001) / FOR: (ROYAL CONSTRUCOES | M114: 000054 | N114: 000132 | O114: 33.809,00 | P114: 0,00 | Q114: 0,00 | R114: 0,00 | S114: 0,00 | V114: 211 | W114: 51 | Z114: 010101
A115: =VLOOKUP(F115,'Contas Orç'!A:B,2,0) -> #N/A | B115: =VLOOKUP(C115,Base_20.12!E:E,1,0) -> 0000000026 | C115: 0000000026 | D115: 0001 | E115: 44882 | G115: 305 | H115: 21 | I115: Credito | J115: EM | K115: EM - PED (013495) PROD: (42010009) / FOR: (HYSTER YALE BRASI | M115: 000055 | N115: 000000 | O115: 170.000,00 | P115: 0,00 | Q115: 0,00 | R115: 0,00 | S115: 0,00 | V115: 305 | W115: 21 | Z115: 010101
A116: =VLOOKUP(F116,'Contas Orç'!A:B,2,0) -> #N/A | B116: =VLOOKUP(C116,Base_20.12!E:E,1,0) -> 0000000026 | C116: 0000000026 | D116: 0002 | E116: 44882 | G116: 305 | H116: 21 | I116: Credito | J116: EM | K116: EM - PED (013495) PROD: (42010008) / FOR: (HYSTER YALE BRASI | M116: 000055 | N116: 000000 | O116: 172.000,00 | P116: 0,00 | Q116: 0,00 | R116: 0,00 | S116: 0,00 | V116: 305 | W116: 21 | Z116: 010101
A117: =VLOOKUP(F117,'Contas Orç'!A:B,2,0) -> COMBUSTIVEIS | B117: =VLOOKUP(C117,Base_20.12!E:E,1,0) -> 0000000027 | C117: 0000000027 | D117: 0001 | E117: 44882 | F117: 330301001 | G117: 209 | H117: 11 | I117: Credito | J117: EM | K117: EM - PED (013496) PROD: (11100008) / FOR: (PETROTUDO COMERCI | M117: 000055 | N117: 000000 | O117: 64.090,00 | P117: 0,00 | Q117: 0,00 | R117: 0,00 | S117: 0,00 | V117: 209 | W117: 11 | Z117: 010101
A118: =VLOOKUP(F118,'Contas Orç'!A:B,2,0) -> COMBUSTIVEIS | B118: =VLOOKUP(C118,Base_20.12!E:E,1,0) -> 0000000027 | C118: 0000000027 | D118: 0002 | E118: 44882 | F118: 330301001 | G118: 209 | H118: 21 | I118: Credito | J118: EM | K118: EM - PED (013496) PROD: (11100008) / FOR: (PETROTUDO COMERCI | M118: 000055 | N118: 000000 | O118: 64.090,00 | P118: 0,00 | Q118: 0,00 | R118: 0,00 | S118: 0,00 | V118: 209 | W118: 21 | Z118: 010101
A119: =VLOOKUP(F119,'Contas Orç'!A:B,2,0) -> PECAS E ACESSORIOS | B119: =VLOOKUP(C119,Base_20.12!E:E,1,0) -> 0000000028 | C119: 0000000028 | D119: 0001 | E119: 44882 | F119: 320301004 | G119: 304 | H119: 11 | I119: Credito | J119: EM | K119: EM - PED (013500) PROD: (22010002) / FOR: (FREIO DIESEL PECA | M119: 000055 | N119: 000000 | O119: 398,00 | P119: 0,00 | Q119: 0,00 | R119: 0,00 | S119: 0,00 | V119: 304 | W119: 11 | Z119: 010101
A120: =VLOOKUP(F120,'Contas Orç'!A:B,2,0) -> PJ-OUTROS SERVICOS CONTRATADOS-PJ | B120: =VLOOKUP(C120,Base_20.12!E:E,1,0) -> 0000000029 | C120: 0000000029 | D120: 0001 | E120: 44882 | F120: 330201006 | G120: 201 | H120: 90 | I120: Credito | J120: EM | K120: EM - PED (013499) PROD: (23010016) / FOR: (APROVADOR SISTEMA | M120: 000055 | N120: 000000 | O120: 499,00 | P120: 0,00 | Q120: 0,00 | R120: 0,00 | S120: 0,00 | V120: 201 | W120: 90 | Z120: 010101
A121: =VLOOKUP(F121,'Contas Orç'!A:B,2,0) -> PJ-OUTROS SERVICOS CONTRATADOS-PJ | B121: =VLOOKUP(C121,Base_20.12!E:E,1,0) -> 0000000029 | C121: 0000000029 | D121: 0002 | E121: 44882 | F121: 330201006 | G121: 201 | H121: 90 | I121: Credito | J121: EM | K121: EM - PED (013499) PROD: (23010016) / FOR: (APROVADOR SISTEMA | M121: 000055 | N121: 000000 | O121: 499,00 | P121: 0,00 | Q121: 0,00 | R121: 0,00 | S121: 0,00 | V121: 201 | W121: 90 | Z121: 010101
A122: =VLOOKUP(F122,'Contas Orç'!A:B,2,0) -> PJ-OUTROS SERVICOS CONTRATADOS-PJ | B122: =VLOOKUP(C122,Base_20.12!E:E,1,0) -> 0000000029 | C122: 0000000029 | D122: 0003 | E122: 44882 | F122: 330201006 | G122: 201 | H122: 90 | I122: Credito | J122: EM | K122: EM - PED (013499) PROD: (23010016) / FOR: (APROVADOR SISTEMA | M122: 000055 | N122: 000000 | O122: 499,00 | P122: 0,00 | Q122: 0,00 | R122: 0,00 | S122: 0,00 | V122: 201 | W122: 90 | Z122: 010101
A123: =VLOOKUP(F123,'Contas Orç'!A:B,2,0) -> PJ-OUTROS SERVICOS CONTRATADOS-PJ | B123: =VLOOKUP(C123,Base_20.12!E:E,1,0) -> 0000000029 | C123: 0000000029 | D123: 0004 | E123: 44882 | F123: 330201006 | G123: 201 | H123: 90 | I123: Credito | J123: EM | K123: EM - PED (013499) PROD: (23010016) / FOR: (APROVADOR SISTEMA | M123: 000055 | N123: 000000 | O123: 499,00 | P123: 0,00 | Q123: 0,00 | R123: 0,00 | S123: 0,00 | V123: 201 | W123: 90 | Z123: 010101
A124: =VLOOKUP(F124,'Contas Orç'!A:B,2,0) -> PJ-OUTROS SERVICOS CONTRATADOS-PJ | B124: =VLOOKUP(C124,Base_20.12!E:E,1,0) -> 0000000029 | C124: 0000000029 | D124: 0005 | E124: 44882 | F124: 330201006 | G124: 201 | H124: 90 | I124: Credito | J124: EM | K124: EM - PED (013499) PROD: (23010016) / FOR: (APROVADOR SISTEMA | M124: 000055 | N124: 000000 | O124: 499,00 | P124: 0,00 | Q124: 0,00 | R124: 0,00 | S124: 0,00 | V124: 201 | W124: 90 | Z124: 010101
A125: =VLOOKUP(F125,'Contas Orç'!A:B,2,0) -> PJ-OUTROS SERVICOS CONTRATADOS-PJ | B125: =VLOOKUP(C125,Base_20.12!E:E,1,0) -> 0000000029 | C125: 0000000029 | D125: 0006 | E125: 44882 | F125: 330201006 | G125: 201 | H125: 90 | I125: Credito | J125: EM | K125: EM - PED (013499) PROD: (23010016) / FOR: (APROVADOR SISTEMA | M125: 000055 | N125: 000000 | O125: 499,00 | P125: 0,00 | Q125: 0,00 | R125: 0,00 | S125: 0,00 | V125: 201 | W125: 90 | Z125: 010101
A126: =VLOOKUP(F126,'Contas Orç'!A:B,2,0) -> PJ-LOCACAO DE MAQUINAS E EQUIPAMENTO | B126: =VLOOKUP(C126,Base_20.12!E:E,1,0) -> 0000000030 | C126: 0000000030 | D126: 0001 | E126: 44882 | F126: 320201004 | G126: 301 | H126: 90 | I126: Credito | J126: EM | K126: EM - PED (013498) PROD: (23010005) / FOR: (COMPANHIA DE LOCA | M126: 000055 | N126: 000000 | O126: 3.631,00 | P126: 0,00 | Q126: 0,00 | R126: 0,00 | S126: 0,00 | V126: 301 | W126: 90 | Z126: 010101
A127: =VLOOKUP(F127,'Contas Orç'!A:B,2,0) -> PJ-LOCACAO DE MAQUINAS E EQUIPAMENTO | B127: =VLOOKUP(C127,Base_20.12!E:E,1,0) -> 0000000030 | C127: 0000000030 | D127: 0002 | E127: 44882 | F127: 320201004 | G127: 301 | H127: 90 | I127: Credito | J127: EM | K127: EM - PED (013498) PROD: (23010005) / FOR: (COMPANHIA DE LOCA | M127: 000055 | N127: 000000 | O127: 3.701,00 | P127: 0,00 | Q127: 0,00 | R127: 0,00 | S127: 0,00 | V127: 301 | W127: 90 | Z127: 010101
A128: =VLOOKUP(F128,'Contas Orç'!A:B,2,0) -> PJ-LOCACAO DE MAQUINAS E EQUIPAMENTO | B128: =VLOOKUP(C128,Base_20.12!E:E,1,0) -> 0000000030 | C128: 0000000030 | D128: 0003 | E128: 44882 | F128: 320201004 | G128: 301 | H128: 90 | I128: Credito | J128: EM | K128: EM - PED (013498) PROD: (23010005) / FOR: (COMPANHIA DE LOCA | M128: 000055 | N128: 000000 | O128: 1.885,00 | P128: 0,00 | Q128: 0,00 | R128: 0,00 | S128: 0,00 | V128: 301 | W128: 90 | Z128: 010101
... A260: =VLOOKUP(F260,'Contas Orç'!A:B,2,0) -> PJ-OUTROS SERVICOS CONTRATADOS-PJ | B260: =VLOOKUP(C260,Base_20.12!E:E,1,0) -> 0000000077 | C260: 0000000077 | D260: 0002 | E260: 44886 | F260: 330201006 | G260: 201 | H260: 90 | I260: Debito | J260: EM | K260: EM - PED (013507) PROD: (23010006) / FOR: (BERNUTTY TECHNOLO | M260: 000054 | N260: 000070 | O260: 586,34 | P260: 0,00 | Q260: 0,00 | R260: 0,00 | S260: 0,00 | V260: 201 | W260: 90 | Z260: 010101
A261: =VLOOKUP(F261,'Contas Orç'!A:B,2,0) -> RECEITA BRUTA DE TRANSPORTES | B261: =VLOOKUP(C261,Base_20.12!E:E,1,0) -> 0000000078 | C261: 0000000078 | D261: 0001 | E261: 44888 | F261: 310101 | G261: 304 | H261: 11 | I261: Credito | J261: RE | K261: RE - NF (000053700) P: (21010001) C: (HAMBURG SUD A/S) | M261: 000101 | N261: 000132 | O261: 1.582,57 | P261: 0,00 | Q261: 0,00 | R261: 0,00 | S261: 0,00 | T261: ORC2022_2 | V261: 304 | W261: 11 | Z261: 010101
A262: =VLOOKUP(F262,'Contas Orç'!A:B,2,0) -> IMOBILIZADO EM ANDAMENTO - PROPRIOS | B262: =VLOOKUP(C262,Base_20.12!E:E,1,0) -> 0000000079 | C262: 0000000079 | D262: 0001 | E262: 44888 | F262: 120307001 | G262: 211 | H262: 51 | I262: Credito | J262: EM | K262: EM - PED (013508) PROD: (11100029) / FOR: (POSTO PECEM COMER | M262: 000055 | N262: 000000 | O262: 241,77 | P262: 0,00 | Q262: 0,00 | R262: 0,00 | S262: 0,00 | T262: ORC2022_2 | V262: 211 | W262: 51 | Z262: 010101
A263: =VLOOKUP(F263,'Contas Orç'!A:B,2,0) -> IMOBILIZADO EM ANDAMENTO - PROPRIOS | B263: =VLOOKUP(C263,Base_20.12!E:E,1,0) -> 0000000079 | C263: 0000000079 | D263: 0002 | E263: 44888 | F263: 120307001 | G263: 211 | H263: 51 | I263: Credito | J263: EM | K263: EM - PED (013508) PROD: (11100029) / FOR: (POSTO PECEM COMER | M263: 000055 | N263: 000000 | O263: 1.278,34 | P263: 0,00 | Q263: 0,00 | R263: 0,00 | S263: 0,00 | T263: ORC2022_2 | V263: 211 | W263: 51 | Z263: 010101
A264: =VLOOKUP(F264,'Contas Orç'!A:B,2,0) -> IMOBILIZADO EM ANDAMENTO - PROPRIOS | B264: =VLOOKUP(C264,Base_20.12!E:E,1,0) -> 0000000079 | C264: 0000000079 | D264: 0003 | E264: 44888 | F264: 120307001 | G264: 211 | H264: 51 | I264: Credito | J264: EM | K264: EM - PED (013508) PROD: (11100008) / FOR: (POSTO PECEM COMER | M264: 000055 | N264: 000000 | O264: 291,20 | P264: 0,00 | Q264: 0,00 | R264: 0,00 | S264: 0,00 | T264: ORC2022_2 | V264: 211 | W264: 51 | Z264: 010101
A265: =VLOOKUP(F265,'Contas Orç'!A:B,2,0) -> IMOBILIZADO EM ANDAMENTO - PROPRIOS | B265: =VLOOKUP(C265,Base_20.12!E:E,1,0) -> 0000000079 | C265: 0000000079 | D265: 0004 | E265: 44888 | F265: 120307001 | G265: 211 | H265: 51 | I265: Credito | J265: EM | K265: EM - PED (013508) PROD: (11100029) / FOR: (POSTO PECEM COMER | M265: 000055 | N265: 000000 | O265: 49,92 | P265: 0,00 | Q265: 0,00 | R265: 0,00 | S265: 0,00 | T265: ORC2022_2 | V265: 211 | W265: 51 | Z265: 010101
A266: =VLOOKUP(F266,'Contas Orç'!A:B,2,0) -> IMOBILIZADO EM ANDAMENTO - PROPRIOS | B266: =VLOOKUP(C266,Base_20.12!E:E,1,0) -> 0000000079 | C266: 0000000079 | D266: 0005 | E266: 44888 | F266: 120307001 | G266: 211 | H266: 51 | I266: Credito | J266: EM | K266: EM - PED (013508) PROD: (11100032) / FOR: (POSTO PECEM COMER | M266: 000055 | N266: 000000 | O266: 205,59 | P266: 0,00 | Q266: 0,00 | R266: 0,00 | S266: 0,00 | T266: ORC2022_2 | V266: 211 | W266: 51 | Z266: 010101
A267: =VLOOKUP(F267,'Contas Orç'!A:B,2,0) -> IMOBILIZADO EM ANDAMENTO - PROPRIOS | B267: =VLOOKUP(C267,Base_20.12!E:E,1,0) -> 0000000079 | C267: 0000000079 | D267: 0006 | E267: 44888 | F267: 120307001 | G267: 211 | H267: 51 | I267: Credito | J267: EM | K267: EM - PED (013508) PROD: (11100032) / FOR: (POSTO PECEM COMER | M267: 000055 | N267: 000000 | O267: 49,90 | P267: 0,00 | Q267: 0,00 | R267: 0,00 | S267: 0,00 | T267: ORC2022_2 | V267: 211 | W267: 51 | Z267: 010101
A268: =VLOOKUP(F268,'Contas Orç'!A:B,2,0) -> IMOBILIZADO EM ANDAMENTO - PROPRIOS | B268: =VLOOKUP(C268,Base_20.12!E:E,1,0) -> 0000000080 | C268: 0000000080 | D268: 0001 | E268: 44888 | F268: 120307001 | G268: 211 | H268: 51 | I268: Credito | J268: EM | K268: EM - PED (013509) PROD: (23010001) / FOR: (EJR CONSTRUCOES E | M268: 000055 | N268: 000000 | O268: 20.924,58 | P268: 0,00 | Q268: 0,00 | R268: 0,00 | S268: 0,00 | T268: ORC2022_2 | V268: 211 | W268: 51 | Z268: 010101
A269: =VLOOKUP(F269,'Contas Orç'!A:B,2,0) -> RECEITA BRUTA DE OPERACOES PORTUARIAS | B269: =VLOOKUP(C269,Base_20.12!E:E,1,0) -> #N/A | C269: 0000000081 | D269: 0001 | E269: 44888 | F269: 310102 | G269: 305 | H269: 42 | I269: Credito | J269: RE | K269: RE - NF (000002341) P: (21020003) C: (VESTAS DO BRASIL ENERG | M269: 000101 | N269: 000032 | O269: 220,00 | P269: 0,00 | Q269: 0,00 | R269: 0,00 | S269: 0,00 | T269: ORC2022_2 | V269: 305 | W269: 42 | Z269: 010101
A270: =VLOOKUP(F270,'Contas Orç'!A:B,2,0) -> RECEITA BRUTA DE OPERACOES PORTUARIAS | B270: =VLOOKUP(C270,Base_20.12!E:E,1,0) -> #N/A | C270: 0000000081 | D270: 0002 | E270: 44888 | F270: 310102 | G270: 305 | H270: 42 | I270: Credito | J270: RE | K270: RE - NF (000002341) P: (21020037) C: (VESTAS DO BRASIL ENERG | M270: 000101 | N270: 000032 | O270: 2.695,00 | P270: 0,00 | Q270: 0,00 | R270: 0,00 | S270: 0,00 | T270: ORC2022_2 | V270: 305 | W270: 42 | Z270: 010101
A271: =VLOOKUP(F271,'Contas Orç'!A:B,2,0) -> RECEITA BRUTA DE OPERACOES PORTUARIAS | B271: =VLOOKUP(C271,Base_20.12!E:E,1,0) -> #N/A | C271: 0000000081 | D271: 0003 | E271: 44888 | F271: 310102 | G271: 305 | H271: 42 | I271: Credito | J271: RE | K271: RE - NF (000002341) P: (21020016) C: (VESTAS DO BRASIL ENERG | M271: 000101 | N271: 000032 | O271: 363,00 | P271: 0,00 | Q271: 0,00 | R271: 0,00 | S271: 0,00 | T271: ORC2022_2 | V271: 305 | W271: 42 | Z271: 010101
A272: =VLOOKUP(F272,'Contas Orç'!A:B,2,0) -> RECEITA BRUTA DE OPERACOES PORTUARIAS | B272: =VLOOKUP(C272,Base_20.12!E:E,1,0) -> #N/A | C272: 0000000081 | D272: 0004 | E272: 44888 | F272: 310102 | G272: 305 | H272: 42 | I272: Credito | J272: RE | K272: RE - NF (000002341) P: (21020024) C: (VESTAS DO BRASIL ENERG | M272: 000101 | N272: 000032 | O272: 440,00 | P272: 0,00 | Q272: 0,00 | R272: 0,00 | S272: 0,00 | T272: ORC2022_2 | V272: 305 | W272: 42 | Z272: 010101
... A296: =VLOOKUP(F296,'Contas Orç'!A:B,2,0) -> RECEITA BRUTA DE TRANSPORTES | B296: =VLOOKUP(C296,Base_20.12!E:E,1,0) -> #N/A | C296: 0000000102 | D296: 0001 | E296: 44889 | F296: 310101 | G296: 304 | H296: 11 | I296: Credito | J296: RE | K296: RE - NF (000002344) P: (21010003) C: (PONTES INDUSTRIA DE CE | M296: 000101 | N296: 000032 | O296: 1.646,89 | P296: 0,00 | Q296: 0,00 | R296: 0,00 | S296: 0,00 | T296: ORC2022_2 | V296: 304 | W296: 11 | Z296: 010101
A297: =VLOOKUP(F297,'Contas Orç'!A:B,2,0) -> #N/A | B297: =VLOOKUP(C297,Base_20.12!E:E,1,0) -> #N/A
A298: =VLOOKUP(F298,'Contas Orç'!A:B,2,0) -> #N/A | B298: =VLOOKUP(C298,Base_20.12!E:E,1,0) -> #N/A
A299: =VLOOKUP(F299,'Contas Orç'!A:B,2,0) -> #N/A | B299: =VLOOKUP(C299,Base_20.12!E:E,1,0) -> #N/A
A300: =VLOOKUP(F300,'Contas Orç'!A:B,2,0) -> #N/A | B300: =VLOOKUP(C300,Base_20.12!E:E,1,0) -> #N/A
A301: =VLOOKUP(F301,'Contas Orç'!A:B,2,0) -> #N/A | B301: =VLOOKUP(C301,Base_20.12!E:E,1,0) -> #N/A
A302: =VLOOKUP(F302,'Contas Orç'!A:B,2,0) -> #N/A | B302: =VLOOKUP(C302,Base_20.12!E:E,1,0) -> #N/A
A303: =VLOOKUP(F303,'Contas Orç'!A:B,2,0) -> #N/A | B303: =VLOOKUP(C303,Base_20.12!E:E,1,0) -> #N/A
A304: =VLOOKUP(F304,'Contas Orç'!A:B,2,0) -> #N/A | B304: =VLOOKUP(C304,Base_20.12!E:E,1,0) -> #N/A
A305: =VLOOKUP(F305,'Contas Orç'!A:B,2,0) -> #N/A | B305: =VLOOKUP(C305,Base_20.12!E:E,1,0) -> #N/A
A306: =VLOOKUP(F306,'Contas Orç'!A:B,2,0) -> #N/A | B306: =VLOOKUP(C306,Base_20.12!E:E,1,0) -> #N/A
A307: =VLOOKUP(F307,'Contas Orç'!A:B,2,0) -> #N/A | B307: =VLOOKUP(C307,Base_20.12!E:E,1,0) -> #N/A
A308: =VLOOKUP(F308,'Contas Orç'!A:B,2,0) -> #N/A | B308: =VLOOKUP(C308,Base_20.12!E:E,1,0) -> #N/A

Sheet Planilha1
A2: COMPETÊNCIA | B2: 44866
A4: Soma de Valor | B4: Rótulos de Coluna
A5: Rótulos de Linha | B5: 0R | C5: EM | D5: RE | E5: SALDO
A6: 120302001 - MOVEIS E UTENSILIOS | B6: 0 | C6: 9.96 | D6: 5562.62 | E6: =B6-C6-D6 -> -5572.58
A7: 120307001 - IMOBILIZADO EM ANDAMENTO - PROPRIOS | B7: 0 | C7: 2.2737368e-12 | D7: 24610.18 | E7: =B7-C7-D7 -> -24610.18
A8: 310101 - RECEITA BRUTA DE TRANSPORTES | B8: 1550796.5 | C8: 0 | D8: 101736.94 | E8: =B8-C8-D8 -> 1449059.5
A9: 310102 - RECEITA BRUTA DE OPERACOES PORTUARIAS | B9: 11333539 | C9: 0 | D9: 0 | E9: =B9-C9-D9 -> 11333539
A10: 310109 - ( - ) DEDUCOES DA RECEITA BRUTA | B10: 1968645.2 | C10: 0 | D10: 0 | E10: =B10-C10-D10 -> 1968645.2
A11: 310901 - OUTRAS RECEITAS | B11: 217883.2 | C11: 0 | D11: 52.95 | E11: =B11-C11-D11 -> 217830.25
A12: 320101 - REMUNERACOES | B12: 1516567.3 | C12: 0 | D12: -9.99 | E12: =B12-C12-D12 -> 1516577.3
A13: 320102 - ENCARGOS SOCIAIS | B13: 254000.43 | C13: 0 | D13: 0 | E13: =B13-C13-D13 -> 254000.43
A14: 320103 - BENEFICIOS | B14: 391504.25 | C14: 0 | D14: -106245.57 | E14: =B14-C14-D14 -> 497749.82
A15: 320104 - OUTROS GASTOS COM PESSOAL | B15: 43720.33 | C15: 0 | D15: 0 | E15: =B15-C15-D15 -> 43720.33
A16: 320201001 - PJ-CONSULTORIA E ASSESSORIA | B16: 22613.09 | C16: 0 | D16: 0 | E16: =B16-C16-D16 -> 22613.09
A17: 320201004 - PJ-LOCACAO DE MAQUINAS E EQUIPAMENTO | B17: 462494.14 | C17: 14849.38 | D17: 29694.62 | E17: =B17-C17-D17 -> 417950.14
... A70: Total Geral | B70: 26401932 | C70: 113616.36 | D70: 372227.4 | E70: =B70-C70-D70 -> 25916088

Sheet Stênio
A1: COMPETÊNCIA | B1: 44866
A3: Soma de Valor | B3: Rótulos de Coluna
A4: Rótulos de Linha | B4: 0R | C4: EM | D4: RE
A5: 120302001 - MOVEIS E UTENSILIOS | B5: 0 | C5: 9.96 | D5: 5562.62
A6: 120307001 - IMOBILIZADO EM ANDAMENTO - PROPRIOS | B6: 0 | C6: 2.2737368e-12 | D6: 24610.18
A7: 310101 - RECEITA BRUTA DE TRANSPORTES | B7: 1550796.5 | C7: 0 | D7: 101736.94
A8: 310102 - RECEITA BRUTA DE OPERACOES PORTUARIAS | B8: 11333539 | C8: 0 | D8: 0
A9: 310109 - ( - ) DEDUCOES DA RECEITA BRUTA | B9: 1968645.2 | C9: 0 | D9: 0
A10: 310901 - OUTRAS RECEITAS | B10: 217883.2 | C10: 0 | D10: 52.95
A11: 320101 - REMUNERACOES | B11: 1516567.3 | C11: 0 | D11: -9.99
A12: 320102 - ENCARGOS SOCIAIS | B12: 254000.43 | C12: 0 | D12: 0
A13: 320103 - BENEFICIOS | B13: 391504.25 | C13: 0 | D13: -106245.57
A14: 320104 - OUTROS GASTOS COM PESSOAL | B14: 43720.33 | C14: 0 | D14: 0
A15: 320201001 - PJ-CONSULTORIA E ASSESSORIA | B15: 22613.09 | C15: 0 | D15: 0
A16: 320201004 - PJ-LOCACAO DE MAQUINAS E EQUIPAMENTO | B16: 462494.14 | C16: 14849.38 | D16: 29694.62
... A73: 380201 - DESPESAS FINANCEIRAS | B73: 1098369.9 | C73: 0 | D73: 2.99
